Workbook

Sheet Cover
A1: NEXCORT IQ
A2: INTERNAL PRICING GUIDE — CONFIDENTIAL
A3: Intelligence at the Speed of Response
A6: HOW TO USE THIS GUIDE
A7: Public-facing language: | B7: "Tailored deployment" · "Custom quote" · "Scaled for agency needs" · "Contact sales"
A8: Internal pricing basis: | B8: Agency size · Dispatcher seats · PSAPs / sites · Call volume · CAD complexity · Security requirements · Add-ons · Support level
A9: Color convention: | B9: Blue text = hardcoded input (editable) · Green text = Included · Grey = Limited · Red = Add-on
A10: Discounting: | B10: See Discounting Rules tab — Sales Director approval required for >15% discount
A11: CAD write-back rule: | B11: Do NOT include full CAD write-back in pilot base pricing — scope separately after discovery
A12: Catalog date: October 2026 — aligned to live addon-catalog + RFP 2396IP Venue Security Dept rates (Javits)
A13: SHEET INDEX
A14: Sheet | B14: Description
A15: 1. Essential Plan | B15: Base subscription, overage, capabilities for small agencies
A16: 2. Professional Plan | B16: Growing counties/cities, full feature set, QA included
A17: 3. Command Plan | B17: Large agencies, command center, up to 75 seats
A18: 4. Enterprise & Statewide | B18: Multi-agency, 50–500+ seats, custom programs
A19: 5. CAD Integration | B19: Discovery → coordination → read-only → write-back tiers
A20: 6. AI & Call Intelligence | B20: Triage, confidence scoring, summarization, custom tuning
A21: 7. Transcription & Translation | B21: Enhanced accuracy, diarization, live translation, language packs
A22: 8. Caller Media | B22: SMS, photo upload, video upload, live streaming, redaction
A23: 9. Supervisor & QA | B23: Scorecards, coaching, dashboards, QA rubrics
A24: 10. Incident Command | B24: War rooms, command dashboards, runbooks, stakeholder pages
A25: 11. Reliability & Tech Ops | B25: Monitoring integrations, SLOs, alert correlation, on-call routing
... A32: 18. Discounting Rules | B32: Approval thresholds, discount caps, strategic guidance
A34: 19. RC Campus — Per-student annual pricing · $1.40/student/yr · min $15K
A35: 20. RC Venue — Venue & event security · capacity-based annual pricing
A36: 21. RC Hospital — Hospital & healthcare · facility-based annual pricing
A37: 22. RC Transit — Transit & transportation · fleet-based annual pricing
A38: 23. Verticals Overview — All 5 product verticals — side-by-side comparison
A39: 24. Feature Add-Ons — QR & NFC · Agency Share · NexIQ Vision™ · Call Assist · iQ Reporting · Command Intelligence · Vault · RCS · CAD Mesh · NG911 Assist
A40: 25. Sales Definitions — In-depth sales language for every sellable service / SKU | B40: Pitch, buyer, positioning, and ‘what it is not’ — no prices

Sheet Sales Definitions
A1: NEXCORT IQ — INTERNAL PRICING GUIDE
A2: SALES DEFINITIONS (Catalog date: October 2026)
A3: In-depth sales definitions for every sellable service — how to explain it, who buys it, how to position it, and what it is not. Not a technical design doc. Prices live on the other tabs; this tab is language only.
A4: HOW TO USE: Filter by Category. Use column D on calls and in proposals. Column G prevents overselling. Yellow cells on Quote Builder still hold prices — this tab is words only.
A5: Category | B5: Service / SKU | C5: One-Line Pitch | D5: Sales Definition (in depth) | E5: Who Buys This | F5: How to Sell It | G5: What It Is NOT | H5: See Sheet
A6: BASE PLANS
A7: Base Plans | B7: NexCort iQ Essential | C7: AI-assisted intake for small PSAPs without replacing CAD. | D7: Essential is the low-risk entry plan for small municipalities, single-site PSAPs, and grant-funded pilots (typically up to ~10 dispatcher seats). The agency gets the web and desktop apps, RBAC, core reporting, audit logs, AI-assisted intake, live transcription, and basic call workflows. Full dispatcher console, deep QA, and full multilingual depth stay Limited — those are the Professional upsell. Position Essential as modernization that sits beside their existing CAD and telephony, not a rip-and-replace. Recommended for first-reference customers and 90-day pilots. | E7: Small city / town PSAPs, pilot sponsors, grant-funded first deployments | F7: Lead with low commitment and grant fit. Show intake + transcription value in week one. Park CAD write-back and Command suites for later. | G7: Not a full command platform; not a CAD replacement; not full QA/translation out of the box | H7: Essential
A8: Base Plans | B8: NexCort iQ Professional | C8: Full intelligence layer for growing counties and cities — translation, QA, and analytics included. | D8: Professional is the standard production plan for growing counties and mid-size cities (typically up to ~25 dispatcher seats). It includes everything in Essential plus the full dispatcher monitoring console, live translation, caller photo/video upload, supervisor QA tools, scorecards, coaching notes, team dashboards, and incident timeline reconstruction. Priority support is included. This is the plan most agencies should land on after a successful Essential pilot. Major incident / war-room / reliability suites remain add-ons or Command upgrades. | E8: County and city ECC directors, supervisors who want QA + translation without Command complexity | F8: Sell the jump from Limited → Included: translation, QA, media, and supervisor dashboards. Use pilot results to justify the step-up. | G8: Not regional command / multi-EOC; not automatic CAD write-back; war rooms still add-on | H8: Professional
A9: Base Plans | B9: NexCort iQ Command | C9: Command and coordination platform for large agencies and major-incident environments. | D9: Command is for large agencies and regional command environments (typically up to ~75 seats) that need major-incident management, command dashboards, war rooms, runbooks, stakeholder status pages, alert correlation, escalation, on-call routing, and reliability reporting — all included. Use this when the buyer’s pain is coordination across teams and partners during storms, MCI, or large events — not just call-taking. Premium onboarding and dedicated rollout planning are included. Custom CAD connectors and dedicated support engineers remain scoped add-ons. | E9: Large PSAPs, regional centers, agencies with formal EOC / major-incident programs | F9: Lead with war rooms, runbooks, and command dashboards. Emphasize coordination value during the last big event they remember. | G9: Not Enterprise multi-agency statewide; not a free path to CAD mesh or write-back | H9: Command
A10: Base Plans | B10: NexCort iQ Enterprise / Statewide | C10: Custom multi-agency or statewide programs — priced and scoped as a program, not a menu. | D10: Enterprise covers multi-agency, statewide, or complex multi-site programs (often 50–500+ seats) with custom security reviews, multi-site deployment support, and negotiated commercial terms. Do not quote Enterprise from a simple seat calculator — engage Solutions / Sales Director early. Expect longer discovery, multiple stakeholders (state 911 boards, shared CAD vendors, IT security), and staged rollouts by agency or region. | E10: State 911 authorities, multi-jurisdiction consortia, large metro consolidations | F10: Treat as a program sale: discovery workshop → phased SOW → reference architecture. Never discount below Discounting Rules without approval. | G10: Not a self-serve SKU; not a one-week pilot package | H10: Enterprise
A11: PRODUCT VERTICALS
A12: Product Verticals | B12: RC Campus | C12: Campus safety reporting layer — QR/NFC/SMS tips without forcing an app download. | D12: RC Campus is sold to universities, colleges, and K–12 on a per-enrolled-student annual model (see Campus sheet for rate and minimums). Students and staff report via QR, NFC, or SMS; campus security gets a dedicated console — not the 911 dispatcher workspace. Base includes tip intake, two-way chat, photo/video, incident timeline, basic Clery documentation log, and campus RBAC. Upsell AI summary, advanced Clery, zone QR, NexIQ Vision™, translation, analytics, Agency Share, and SMS location. Position as the missing safety layer between ‘call 911’ and ‘ignore it.’ | E12: Campus safety directors, Clery coordinators, university IT / risk | F12: Open with ‘no app download’ and Clery documentation. Land with tip adoption; expand into Vision, Clery module, and alerts. | G12: Not a PSAP CAD console; basic Clery log is not the full Clery Act Compliance Module / legal advice | H12: RC Campus
A13: Product Verticals | B13: RC Venue | C13: Fan-to-security reporting for stadiums, arenas, and events — zone-aware, no app required. | D13: RC Venue prices by venue capacity tier (annual). Guests report from QR/NFC/SMS tied to section, gate, or zone; venue security and supervisors work an orange-branded venue console. Guest Services is a separate non-emergency console and must never be sold as 911 dispatch. Strong for event operators who already have cameras and access control but lack a guest reporting path into security. Upsell Vision cameras, live video, analytics, translation, and event-day onsite support. Also sell Venue Security Department licensing (named-seat list $2,133/user/yr or site-wide dept package) for convention-center / staff incident reporting — see RC Venue sheet (RFP 2396IP). | E13: Venue GMs, event security directors, stadium operations | F13: Demo a section-level tip into the security console. Separate Guest Services from Security in every conversation. | G13: Not a 911 ECC product; Guest Services console is not emergency dispatch | H13: RC Venue
A14: Product Verticals | B14: RC Hospital | C14: Hospital capacity and pre-alert coordination for EMS–hospital handoffs and MCI readiness. | D14: RC Hospital is facility/bed-tier annual pricing for hospitals and health systems. Hospital staff update capacity and acknowledge pre-alerts in a hospital portal — they do not sit on the PSAP dispatcher console. Base includes staff/supervisor/admin/coordinator views, pre-alert intake, and timelines. Upsell MCI command, EMS data integration, Agency Share, analytics, and Hospital Routing Module. Sell into EMS coordinators and ED leadership who need faster, cleaner pre-alerts — not into the 911 floor as a replacement console. | E14: Hospital EMS coordinators, ED leadership, health-system emergency management | F14: Lead with pre-alert acknowledgment and capacity visibility. Attach MCI module for regional readiness grants. | G14: Not a CAD; not a PSAP dispatch console; not a full EHR | H14: RC Hospital
A15: Product Verticals | B15: RC Transit | C15: Passenger-to-security reporting for bus and rail systems — vehicle and station aware. | D15: RC Transit prices by fleet/system tier (annual). Passengers report via QR/NFC/SMS; transit security and supervisors use a transit ops console. Base includes reporting channels, two-way chat, media intake, timelines, and transit RBAC. Upsell Vision cameras, Agency Share, analytics, translation, SMS location, and alerts. Position for transit authorities that need a passenger safety channel without building a mobile app. | E15: Transit authority security / safety directors, rail and bus ops leadership | F15: Show a vehicle/station tip landing in the transit console. Bundle SMS location for outdoor stops. | G15: Not a PSAP CAD; not AVL by itself (sell Map Unit Overlays separately where CAD/AVL exists) | H15: RC Transit
A16: Product Verticals | B16: Call Assist (non-emergency product) | C16: AI-assisted non-emergency call handling that keeps 911 off the non-emergency queue. | D16: Call Assist is a standalone non-emergency product: greeting flows, classification, callbacks, operator console, and supervisor monitor. Emergency 911 is never in scope — the Safety Engine transfers immediately and that path cannot be suppressed. Users land on /app/call-assist/* — never the 911 dispatcher workspace. Sell to agencies drowning in non-emergency volume who want AI help without putting automation on the 911 console. Module list price is the starting point; CAD push, RMS drafts, TTY, and external routing are optional expansions. Never free. | E16: ECC directors, non-emergency call center managers, city service line operators | F16: Quantify non-emergency volume first. Promise containment and warm transfer — never ‘AI answers 911.’ | G16: Not a 911 dispatcher console; not an unsupervised bot on emergency lines; CAD/RMS push stays human-reviewed | H16: Feature Add-Ons
A17: CAD INTEGRATION
A18: CAD Integration | B18: CAD Discovery Workshop | C18: Paid discovery that decides what CAD integration is actually possible. | D18: A structured workshop with PSAP, IT, and CAD vendor stakeholders to map fields, environments, nature codes, and write-back risk. Sell this before promising any CAD connectivity. Basic / Standard / Advanced tiers exist by complexity. Output should be a field-mapping understanding and a clear go/no-go on read-only vs write-back. Always remind buyers: NexCort iQ enhances CAD — it does not replace it. | E18: Agency IT, CAD admins, ECC leadership | F18: Make discovery a required gate before any integration quote. Use it to protect the deal from over-promising. | G18: Not the integration itself; not permission to enable write-back | H18: CAD Integration
A19: CAD Integration | B19: CAD Read-Only Integration | C19: One-way CAD context into NexCort — zero risk to the system of record. | D19: Pulls CAD incident/unit context into the NexCort workspace so dispatchers see structured CAD data while they work. No write path into CAD. This is the default first integration for every PSAP. Complexity tiers (Simple → Advanced) drive one-time fees. Annual maintenance is typically 15–20% of the integration fee, billed separately. | E19: Agency IT + ECC ops who want intelligence without CAD risk | F19: Position as the safe first step. Prove Context Cards / unit awareness before discussing write-back. | G19: Not write-back; not multi-CAD mesh; not AVL overlays by itself | H19: CAD Integration
A20: CAD Integration | B20: CAD Assisted / Automated Write-Back | C20: Human-reviewed (or tightly gated automated) posting into CAD — never in pilot base. | D20: Assisted write-back lets a dispatcher/supervisor submit proposed CAD updates that require human approve/reject with attestation. Automated write-back is rare, agency-explicit, and still fail-closed at every layer. Requires signed CAD write-back addendum and completed discovery. Complexity tiers set one-time fees. RULE FOR EVERY REP: do not include full CAD write-back in pilot base pricing — scope separately after discovery. | E20: Mature PSAPs with IT sponsorship and vendor cooperation | F20: Sell only after read-only success. Emphasize human review and fail-closed design to CAD vendors and CJIS stakeholders. | G20: Not silent automation by default; not included in pilots; not a substitute for CAD training | H20: CAD Integration
A21: CAD Integration | B21: Multi-CAD Connector / CAD-to-CAD Mesh | C21: Regional multi-CAD awareness for mutual aid — high trust, never free. | D21: Connects multiple CAD systems under one tenant and/or enables controlled CAD-to-CAD mesh awareness across mutual-aid partners. This is a Command+-class commercial SKU and a high-complexity delivery. Never offer complimentary. Expect dual-admin consent patterns similar to Agency Share, careful scoping, and longer timelines. Additional CAD vendor connectors are separate one-time fees. | E21: Regional centers, mutual-aid heavy counties, multi-CAD enterprises | F21: Sell into regional readiness and mutual-aid conversations — not single-agency pilots. | G21: Not free; not a weekend install; not automatic write-back across agencies | H21: Feature Add-Ons / CAD Integration
A22: CAD Integration | B22: Map Unit Overlays (AVL) | C22: See units on the map with status and ETA from the CAD/AVL feed. | D22: Shows real-time apparatus markers on operational maps using the agency’s CAD/AVL feed — unit status, distance, ETA. Command+ monthly add-on. Soft-fails cleanly when the feed is unavailable so the rest of the console still works. Strong visual sell in demos; confirm AVL feed access in discovery. | E22: Dispatchers and supervisors who already have AVL in CAD | F22: Demo during a live or replayed call with unit motion. Confirm feed availability before quoting. | G22: Not a standalone AVL system; not GPS tracking invented by NexCort | H22: Feature Add-Ons / CAD Integration
A23: CAD Integration | B23: NG911 Assist | C23: Helps i3-aware PSAPs with diversion, EIDO/additional data, and NG911 metrics — not a phone system replace. | D23: Assist pack for agencies mid-NG911 / i3 upgrade: diversion support, EIDO/additional data assist, and NG911 metrics. There is no single list SKU in the billing catalog yet — quote after ESInet/i3 discovery using the internal range on Feature Add-Ons. Position as meeting them where their NG911 program is. Do not promise telephony rip-and-replace or ESInet replacement. | E23: PSAP directors and IT leads in active NG911 programs | F23: Ask about ESInet vendor and i3 readiness first. Scope a discovery-led quote — don’t invent a fixed SKU on the call. | G23: Not a CPE/telephony replacement; not automatic NG911 certification | H23: Feature Add-Ons
A24: VISION & CAMERAS
A25: Vision & Cameras | B25: NexIQ Vision™ — Standard / Professional / Enterprise | C25: Agency cameras on the live incident — with AI scene assist for authorized roles. | D25: NexIQ Vision™ (formerly NexCort iQ Connect) links existing ONVIF/RTSP facility cameras into the incident console so responders and dispatch/security see the scene without leaving the workflow. Tiers: Standard (up to 10 cameras), Professional (up to 50), Enterprise (unlimited / multi-site KVS). Includes pathing for AI scene observations and vision transcripts for authorized roles — always human-in-the-loop, never autonomous enforcement or facial-recognition promises unless product docs explicitly support them. Never free. | E25: PSAP supervisors, campus/venue/transit security leaders with camera estates | F25: Ask how many cameras and which zones matter on day one. Start Standard; expand by camera count. | G25: Not a VMS replacement; not autonomous policing; not free ‘camera access’ | H25: Feature Add-Ons
A26: Vision & Cameras | B26: Citizen Camera Share (Ring / Nest / Wyze) | C26: Caller or resident grants a time-limited live camera view into the incident. | D26: Consent-based, time-limited share from citizen cameras (Ring live; Nest/Wyze share paths) into the incident workspace. Strong for residential 911 and campus residential life. Privacy language matters: temporary share with consent — not permanent surveillance takeover. Pair with NexIQ Vision™ agency cameras for a complete ‘see the scene’ story. | E26: Residential-heavy PSAPs, campus safety, community policing programs | F26: Lead with consent and time limits. Demo the one-tap share from SMS where available. | G26: Not permanent camera takeover; not a Ring reseller contract by itself | H26: Feature Add-Ons
A27: Vision & Cameras | B27: Camera Integration Setup (one-time) | C27: Paid setup to bridge cameras correctly the first time. | D27: One-time professional services to configure RTSP/ONVIF bridges, zones, and provider connections per camera provider. Quote per provider when the estate is complex. Prevents ‘cameras don’t show up on go-live’ failures that kill executive confidence. | E27: Agency IT / physical security teams | F27: Always attach setup when selling Vision Professional/Enterprise or multi-provider estates. | G27: Not the monthly Vision subscription | H27: Feature Add-Ons
A28: INTELLIGENCE & ANALYTICS
A29: Intelligence & Analytics | B29: iQ Reporting | C29: Daily agency analytics for leaders — never on the dispatcher console. | D29: iQ Reporting is the supervisor/agency-admin analytics surface across verticals (911, campus, venue, transit, hospital). It answers ‘what happened yesterday/this week’ with daily aggregated metrics — not a live dispatcher tool. RBAC blocks dispatcher and front-line roles. On Professional/Command it is included; on Essential sell it as an add-on aligned to the Command Intelligence list band until a dedicated SKU ships. Use it to win supervisors and agency admins who need accountability reporting for leadership and grants. | E29: Supervisors, agency admins, campus/venue/transit admins — never front-line dispatchers | F29: Show a supervisor-only dashboard. Stress that dispatchers are not distracted by reporting UI. | G29: Not a dispatcher widget; not real-time CAD BI; not public open-data publishing | H29: Feature Add-Ons
A30: Intelligence & Analytics | B30: Command Intelligence | C30: Comms-ops intelligence for supervisors — different from the Incident Command Dashboard. | D30: Command Intelligence is a Professional+ communications operations module: call volume, Call Assist containment, translation breakdown, repeat locations, and drill-downs for supervisors and command staff. It is not the same product as Incident Command Dashboard / war rooms. Sell to leaders who want operational intelligence about how the communications center is performing — especially where Call Assist or translation is in play. | E30: Supervisors, communications managers, command staff | F30: Clarify naming early: ‘Command Intelligence’ ≠ ‘Incident Command.’ Bring containment and repeat-location stories. | G30: Not war rooms / major incident boards; not iQ Reporting’s daily vertical pack (related but distinct) | H30: Feature Add-Ons
A31: Intelligence & Analytics | B31: Incident Context Cards | C31: Prior-call and officer-safety context on the live call — included in every plan. | D31: Read-only cards during live 911/ops calls showing prior calls at the location, officer-safety flags, and labeled CAD/Vault sources. Included in all plans at $0 list — use it as a universal value proof in every demo. Explicitly does not include JMS or criminal-history data. When Vault is purchased, Context Cards get richer historical location intelligence. | E31: Every dispatcher and supervisor on any plan | F31: Open demos with a Context Card on a repeat address. Upsell Vault when they ask for ‘all-time’ history. | G31: Not NCIC/JMS; not criminal history; not a paid upsell by itself | H31: Feature Add-Ons
A32: Intelligence & Analytics | B32: NexiQ Vault | C32: Historical CAD/call archive that makes Context Cards smarter after migrations. | D32: Read-only archive of prior CAD/call-record exports for agencies migrating systems or needing deeper location history. Search by address and enrich Context Cards with all-time intelligence. Command+ monthly add-on. No JMS or criminal-history data. Sell when the agency is mid-CAD migration or complains that ‘we lose history every time we change CAD.’ | E32: Agency admins, supervisors, analysts on Command+ journeys | F32: Attach to CAD migration deals and Context Card demos. Emphasize read-only and no criminal databases. | G32: Not a RMS/JMS; not criminal history; not free | H32: Feature Add-Ons
A33: CONTINUITY & COMMAND
A34: Continuity & Command | B34: Response Continuity System (RCS) | C34: Keeps life-safety calls from falling through silent gaps — monitor, geofence arrival, closure gate. | D34: RCS is a Professional+ life-safety persistence module: silent monitor queue, unit geofence arrival confirmation, audio sentinel, escalation paths, and a closure gate with supervisor-override audit. Sell to agencies worried about calls that go quiet, units that never confirm arrival, or closures without accountability. This is an operations-confidence sale, not a shiny AI demo. | E34: PSAP supervisors and quality/ops leaders with life-safety accountability pressure | F34: Tell the story of a quiet line / unconfirmed arrival. Walk the closure-gate audit path with supervisors. | G34: Not silent illegal wiretaps; not a replacement for unit status in CAD | H34: Feature Add-Ons
A35: Continuity & Command | B35: Mutual Aid & MCI Command | C35: When the incident spans agencies, command still has one coordinated playbook. | D35: Command tooling for mutual-aid activation and multi-casualty coordination across PSAP and hospital participants. Complements war rooms and hospital capacity/routing. Sell into regional readiness and grant-funded MCI modernization. Confirm which agencies and roles are in scope before promising a joint go-live. | E35: Regional EMA, large PSAPs, hospital EMS coordinators | F35: Pair with Hospital Routing / MCI modules and Incident Command suite. Great grant narrative. | G35: Not automatic mutual-aid legal authority; not a radio system | H35: Feature Add-Ons / Incident Command
A36: Continuity & Command | B36: Major Incident Management / Command Dashboard / War Rooms | C36: Structured major-incident coordination instead of scattered phone trees and whiteboards. | D36: These Incident Command add-ons (included in Command plan) give supervisors and command staff status boards, collaborative war rooms, and a decision-support command view while local CAD remains system of record. Sell for storms, active incidents, large events, and EOC activity. On Essential/Professional, package as add-ons; on Command, remind them it’s already in the base so you can sell adjacent modules (PIO view, stakeholder pages, Mutual Aid). | E36: Supervisors, agency admins, EOC liaisons | F36: Replay their last big event. Show war room vs. group text chaos. | G36: Not a replacement CAD; not public mass notification by itself | H36: Incident Command
A37: Continuity & Command | B37: Runbooks / Playbooks | C37: Approved steps under stress — so every shift runs the same play. | D37: Operational runbooks/playbooks attached to incident types so staff follow approved steps during high stress. Content must be agency-owned and kept current — sell the discipline, not just the UI. Included or add-on depending on plan (see Incident Command / plan sheets). | E37: Training officers, supervisors, agency admins | F37: Ask who owns SOPs today. Offer to load their top 5 incident types in onboarding. | G37: Not legal advice; not automatic SOP compliance certification | H37: Incident Command
A38: Continuity & Command | B38: Escalation Bridge (live ops) vs Reliability Escalation Engine | C38: Know which escalation you’re selling — live incident path vs IT/ops reliability path. | D38: Live ops Escalation Bridge routes active incident escalation into supervisor/command workflows. The Reliability Escalation Engine (Reliability Ops sheet) is for platform/IT alert promotion and on-call routing when systems degrade. Do not conflate them on a quote. Both matter; different buyers (ops floor vs agency IT/NOC). | E38: Ops supervisors (live) vs Agency IT / NOC (reliability) | F38: Ask whether the pain is ‘calls escalating’ or ‘systems paging.’ Quote the matching sheet. | G38: Not interchangeable products; not a radio console | H38: Feature Add-Ons / Reliability Ops
A39: AI & CALL INTELLIGENCE
A40: AI & Call Intelligence | B40: AI Triage Workflows | C40: Structured AI prompts during intake — dispatcher stays in control. | D40: Tiered AI triage (Basic → Premium by rule depth) that surfaces protocol-oriented suggestions while the call is live. Always position as decision support, never as replacing dispatcher judgment. Pairs with live transcription; without transcription most AI value collapses. Never offer core AI triage as complimentary on a paid order. | E40: Dispatchers and supervisors; ECC directors buying consistency | F40: Demo mid-call suggestions. Repeat: human remains accountable. | G40: Not autonomous dispatch; not a protocol certification body | H40: AI Intelligence
A41: AI & Call Intelligence | B41: AI Confidence Scoring | C41: Shows when the model is unsure — so staff pause or escalate. | D41: Confidence metadata on AI outputs so dispatchers and supervisors know when to trust, pause, or escalate. Upsell Advanced/Premium when the agency wants multi-factor scoring. Excellent objection-handler for ‘we don’t trust AI’ — you’re selling the brake pedal, not just the engine. | E41: Risk-aware ECC leaders and QA supervisors | F41: Show a low-confidence example and the human override path. | G41: Not a guarantee of correctness; not automatic escalation policy | H41: AI Intelligence
A42: AI & Call Intelligence | B42: AI Incident Summarization | C42: Draft narratives for handoffs and AARs — humans edit before they become record. | D42: Volume-tiered AI summaries that draft incident narratives for handoff and after-action use. Always human-editable. Sell time-back to supervisors and training units. Price by monthly call volume band. | E42: Supervisors, training, agency admins | F42: Show before/after summary time. Keep ‘draft’ language in every proposal. | G42: Not an official CAD narrative without human acceptance | H42: AI Intelligence
A43: AI & Call Intelligence | B43: AI Dispatcher Recommendation Engine | C43: Structured recommendations under pressure — staff remain accountable. | D43: Recommendation engine for dispatcher decisions based on live context. Standard vs Advanced tiers. High-value, high-scrutiny — scope carefully and keep human-accountability language airtight in writing. | E43: Progressive ECC directors with strong training culture | F43: Pair with QA and SOP libraries. Avoid over-promising outcomes. | G43: Not autonomous unit recommendation into CAD | H43: AI Intelligence
A44: AI & Call Intelligence | B44: SOP Protocol AI | C44: AI aligned to the agency’s own SOP/protocol library during intake. | D44: Surfaces agency SOP/protocol guidance during intake so suggestions match local policy, not a generic script. Flag-gated. Sell after you know they have digitizable protocols and an owner who will maintain them. | E44: Training officers, protocol coordinators, supervisors | F44: Ask for their top protocol packs in discovery. Don’t promise content creation for free. | G44: Not a substitute for certified protocol instruction | H44: Feature Add-Ons / product modules
A45: LANGUAGE & TRANSCRIPTION
A46: Language & Transcription | B46: Live Transcription | C46: Every word captured as the call happens — foundation for AI, QA, and audit. | D46: Real-time speech-to-text in the dispatcher workspace. Core differentiator and never free. Transcripts feed AI, QA scorecards, disposition summaries, and audit. If budget is tight, protect transcription before nearly every other add-on — most intelligence value depends on it. Enhanced accuracy tiers upsell cleaner transcripts at higher volumes. | E46: Every PSAP buyer | F46: Make it non-negotiable in Professional+ narratives. Never ‘throw in free.’ | G46: Not a courtroom stenographer guarantee; enhanced accuracy is a separate tier | H46: Transcription / Essential–Command
A47: Language & Transcription | B47: Live Translation (PSAP) | C47: Understand non-English callers faster inside the telecommunicator workflow. | D47: Real-time translation in PSAP intake workflows. Included in Professional+; add-on on Essential. Language packs (Top 10 / Top 15 / custom) deepen coverage. Sell for community language access and equity narratives — and for reducing interpreter wait on common languages. | E47: ECC directors in multilingual communities | F47: On Essential, price translation explicitly. On Pro+, sell language packs for depth. | G47: Not a certified interpreter replacement for every legal scenario | H47: Transcription
A48: Language & Transcription | B48: NexCort Translate (ops / field) | C48: Language access where the public is standing — campus, venue, transit, clinical — not only on the 911 line. | D48: Translation sessions for field and ops consoles outside the classic telecommunicator bridge. Complements PSAP live translation. Sell when the buyer’s language pain is at the point of contact (security desk, guest services, triage desk), not only in the ECC. | E48: Campus/venue/transit/hospital ops leaders | F48: Don’t double-sell against PSAP Live Translation — explain the different venue of use. | G48: Not the same SKU as PSAP Live Translation; not a phone interpreter network contract | H48: Feature Add-Ons
A49: Language & Transcription | B49: Speaker Diarization | C49: Separates who said what — critical for QA and investigations. | D49: Speaker separation on transcripts by volume tier. Sell to QA, training, and agencies with heavy investigation/records needs. Pairs with enhanced transcription. | E49: QA supervisors, training, records/investigations stakeholders | F49: Play a two-speaker sample. Attach to QA suite deals. | G49: Not perfect identity attribution of unknown callers | H49: Transcription
A50: CALLER MEDIA
A51: Caller Media | B51: Caller SMS Link Generation | C51: Send a secure link so the caller can share location or media without installing an app. | D51: Generates time-limited SMS links for location/media workflows. Foundational for silent/text paths and citizen media. Tier by monthly link volume. Combine with photo/video upload and LiveLocation messaging. | E51: Dispatchers and supervisors; campus/transit passenger workflows | F51: Demo the text-the-link moment. Upsell media tiers once SMS adoption is real. | G51: Not guaranteed carrier delivery SLAs; not a mass-notification short code | H51: Caller Media
A52: Caller Media | B52: Caller Photo / Video Upload | C52: Still images and clips that clarify location or hazard before units arrive. | D52: Caller-originated photo and video upload into the incident, with governance/retention controls. Tier by volume and retention. Strong for ‘can’t speak safely’ and hazard identification. Always mention media audit trail for defensibility. | E52: ECC ops; campus/venue security | F52: Show a photo clarifying an address or weapon description. Attach audit trail for counsel/CJIS comfort. | G52: Not live streaming (that’s a separate SKU); not public social media ingest | H52: Caller Media
A53: Caller Media | B53: Live Caller Video Streaming | C53: Narrow live WebRTC view from the caller device with operational discipline. | D53: Real-time caller video into the workspace via consent/SMS flows. Higher-trust, higher-bandwidth than upload. Quote Standard vs Premium carefully; confirm policy for when live video is appropriate. Distinct from NexIQ Vision™ facility cameras. | E53: Supervisors and progressive ECC/campus programs | F53: Separate ‘caller live video’ from ‘facility cameras’ in every proposal line. | G53: Not facility CCTV; not continuous recording of the public without policy | H53: Caller Media
A54: Caller Media | B54: Media Audit Trail / Redaction / Retention | C54: Defensible media handling for investigations, QA, and records requests. | D54: Audit who accessed media, redaction workflows, and retention controls so the platform follows agency hold/purge rules. Sell to counsel, records, and CJIS-minded IT — not as a flashy demo feature. | E54: Agency counsel, records, agency admin/IT | F54: Bring to security review meetings. Bundle with caller media sales. | G54: Not legal privilege advice; not automatic FOIA responses | H54: Caller Media
A55: LOCATION & REPORTING
A56: Location & Reporting | B56: QR & NFC Code Management | C56: Put a report button on every door, stop, and gate — unique URL per location. | D56: Generate unique reporting URLs per location with downloadable QR images and NFC tag URLs. Scan and tap counts tracked separately. Included or add-on by vertical/plan (see Feature Add-Ons matrix). PSAP roles are intentionally excluded from managing campus/venue/transit QR estates — those vertical admins own them. Land-and-expand from Community Connect free tip line into multi-zone paid QR. | E56: Campus, venue, transit admins/supervisors; venue operators | F56: Walk a physical zone story. Upsell analytics and SMS location after adoption. | G56: Not a marketing QR platform; not PSAP-managed for vertical estates | H56: Feature Add-Ons
A57: Location & Reporting | B57: SMS Location Acquisition | C57: Auto-reply a GPS link when someone texts the emergency/reporting number. | D57: When a student, passenger, or tipster texts in, the system can auto-reply with a one-tap location link and track engagement across QR vs NFC vs SMS. Monthly add-on plus setup. Excellent for outdoor campuses and transit stops where address is weak. | E57: Campus safety, transit security, tip-line programs | F57: Demo text → link → pin on map. Attach Location Analytics for leadership reporting. | G57: Not guaranteed precise indoor GPS; not a mass alert short code | H57: Feature Add-Ons
A58: Location & Reporting | B58: Agency Share | C58: Consent-based cross-agency incident awareness — a feature, not a product logo. | D58: Controlled, bidirectional, consent-based sharing of incident context between partner agencies with dual audit trails. Sold as a monthly feature add-on (~$1,500 list), not a separate product brand. Both agencies must authorize. Scope by incident type. Never imply free cross-tenant browsing. | E58: Neighboring PSAPs, campus↔city pairs, hospital↔PSAP partners | F58: Require both sides in the conversation. Use mutual-aid stories. | G58: Not a free mesh; not automatic data sharing; not CAD-to-CAD by itself | H58: Feature Add-Ons
A59: VERTICAL OPS & COMPLIANCE
A60: Vertical Ops & Compliance | B60: Emergency Alert Broadcast (+ Short Code) | C60: Push occupant alerts from campus/venue/transit consoles — be honest about SMS timing. | D60: Mass notification initiated from vertical consoles. Web dashboard delivery for open sessions is fast; dedicated SMS short-code is a separate pass-through with 8–12 week procurement and carrier delivery measured in minutes for large blasts — not sub-3 seconds. Never oversell SMS speed. Pair with Clery/campus safety narratives carefully and truthfully. | E60: Campus/venue/transit admins and supervisors | F60: Sell dashboard alerting first; treat short-code as a procurement project. | G60: Not IPAWS/WEA replacement; not sub-3s SMS to 50k phones | H60: Feature Add-Ons
A61: Vertical Ops & Compliance | B61: Clery Act Compliance Module | C61: Structured Clery workflows for campus — documentation aid, not legal advice. | D61: Campus Command+ module for CSA registry, human classification, Daily Crime Log timing, public crime log, and ASR statistics support. Explicitly does not constitute legal advice. Distinguishes from the lighter ‘basic Clery documentation log’ included in Campus base. Sell to Clery coordinators who are drowning in spreadsheets. | E61: Clery coordinators, campus safety leadership | F61: Never claim ‘makes you Clery compliant.’ Claim ‘structures the workflow and evidence trail.’ | G61: Not legal advice; not automatic classification without humans | H61: Feature Add-Ons / RC Campus
A62: Vertical Ops & Compliance | B62: Physical Security Ingest | C62: Fire panel and access-control events into ops — lock/unlock stays fail-closed. | D62: Ingests physical security events (fire panel, access control) into ops consoles. Outbound lock/unlock commands are a separate fail-closed flag requiring human approval — do not promise automatic door control. Sell to campus/venue physical security teams integrating SOC and safety reporting. | E62: Physical security / SOC managers with campus or venue estates | F62: Confirm event ingest first; treat actuation as a later controlled phase. | G62: Not automatic unlock; not a full access-control admin suite | H62: Feature Add-Ons
A63: Vertical Ops & Compliance | B63: Hospital Routing Module | C63: Divert status, ED routing, and trauma bay awareness for EMS–hospital coordination. | D63: Hospital Professional+ module for divert status, ED routing, trauma bay availability, and related coordination. Complements RC Hospital base and MCI modules. Sell with EMS medical directors and hospital emergency management — keep PSAP vs hospital portal boundaries clear. | E63: Hospital EMS coordinators, ED leadership | F63: Attach to MCI/mutual-aid regional packages. | G63: Not an EHR; not ambulance billing | H63: Feature Add-Ons / RC Hospital
A64: Vertical Ops & Compliance | B64: Venue Guest Services Console | C64: Guest issues and wayfinding — explicitly not emergency dispatch. | D64: Orange-branded console for VENUE_GUEST_SERVICES and related ops. Handles guest issues separately from security command. Every page should reinforce it is not a 911 emergency dispatch system — your proposal language must say the same. Sell to venue GMs who need guest ops without polluting the security stack. | E64: Venue guest services / guest experience leadership | F64: Always dual-track Security vs Guest Services in the org chart discussion. | G64: Not a 911 system; not a security command replacement | H64: Feature Add-Ons / RC Venue
A65: SUPERVISOR & QA
A66: Supervisor & QA | B66: QA Review Tools / Scorecards / Coaching Notes | C66: Structured coaching instead of random call reviews. | D66: Supervisor suite for scoring calls, documenting coaching, and tracking follow-ups. Limited on Essential; included/expanded on Professional+. Bundle Scorecards + Coaching + Team Dashboards at 15% when sold together (see Supervisor QA sheet). Custom QA rubrics are high-value one-time work after pilot. | E66: Supervisors, training coordinators, agency admins | F66: Ask how many calls they QA today. Sell consistency and documentation. | G66: Not automatic HR discipline; AI QA scoring is a separate upsell | H66: Supervisor QA
A67: Supervisor & QA | B67: Team Performance Dashboards / Call Quality Trends | C67: See team strain and whether coaching is working. | D67: Real-time and longitudinal supervisor analytics for team performance and quality trends. Included on Professional+; add-on on Essential. Pair with iQ Reporting for leadership-facing daily packs. | E67: Supervisors and ECC managers | F67: Show trend lines tied to coaching interventions. | G67: Not payroll/HRIS; not public CompStat | H67: Supervisor QA
A68: RELIABILITY & PLATFORM
A69: Reliability & Platform | B69: Monitoring / Alert Correlation / On-Call / SLO Dashboards | C69: IT-grade confidence that the platform is healthy during mission-critical ops. | D69: Reliability Ops add-ons for agencies with NOC/SOC or formal on-call. Included heavily in Command; add-on for lower plans. Sell to Agency IT and NC-coordinated enterprise deals — not as dispatcher toys. | E69: Agency IT, NOC/SOC, enterprise architects | F69: Ask about existing paging tools. Offer CloudWatch dashboard package as one-time accelerant. | G69: Not a general ITSM for the whole city | H69: Reliability Ops
A70: Reliability & Platform | B70: Network Access Controls | C70: Only approved networks and time windows can reach the console. | D70: IP allowlists and time-window gates per user group; blocked attempts audited. Professional+ monthly add-on. Strong for CJIS-minded IT reviews and agencies locking down remote access. | E70: Agency IT / information security | F70: Bring to security questionnaires. Pair with audit retention conversations. | G70: Not a full Zero Trust suite for the entire enterprise | H70: Feature Add-Ons
A71: Reliability & Platform | B71: Deception Shield | C71: Honeypot/decoy surfaces that detect probing before real data is exposed. | D71: Defensive security layer using honeypot fields, synthetic paths, and decoy records to detect unauthorized access, credential stuffing, and insider reconnaissance. Command+ monthly. Sell to security-mature enterprises — explain outcomes in plain language, not malware theatrics. | E71: Agency IT / InfoSec, Enterprise buyers | F71: Position as early-warning for abuse — not as entrapment of legitimate users. | G71: Not offensive security services; not a guarantee against all breaches | H71: Feature Add-Ons
A72: Reliability & Platform | B72: Extended Audit Retention / API Keys & Webhooks | C72: Keep audit longer and connect outbound systems — under agency control. | D72: Extended Audit Retention expands beyond plan retention floors for legal hold and grant reporting. API Keys & Webhooks enable scoped outbound integrations and event subscriptions. Both are monthly platform add-ons. Sell into IT and compliance reviews. | E72: Agency admin/IT, integrators | F72: Ask about retention statutes and existing integration backlog. | G72: Not unlimited public APIs; keys are scoped and revocable | H72: Feature Add-Ons
A73: Reliability & Platform | B73: Grant Success Package | C73: One-time package that makes grant reporting and outcome exports easier. | D73: Documentation packages, reporting templates, and outcome exports formatted for PSAP improvement and emergency-management preparedness grants. One-time (~$2,500 list), Professional+. Excellent closer when budget is grant-shaped. | E73: Grant writers, agency admins, project sponsors | F73: Offer when the funding source is a grant. Don’t pretend it writes the grant narrative for them. | G73: Not a grant-writing service; not guaranteed award | H73: Feature Add-Ons
A74: SERVICES & COMMERCIAL
A75: Services & Commercial | B75: Pilot Programs | C75: Time-boxed proof with clear success criteria — write-back still out of base. | D75: Pre-packaged 90–180 day pilots for Small City, County, Command, and Enterprise profiles (see Pilot Programs sheet). Pilots should prove intake, transcription, supervisor value, and (if scoped) read-only CAD — not full write-back. Always define success metrics and conversion path to annual subscription. | E75: First-time agencies and grant-funded trials | F75: Sell the outcome checklist, not unlimited sandbox time. Protect write-back exclusion in writing. | G75: Not a free forever plan; not full CAD write-back | H75: Pilot Programs
A76: Services & Commercial | B76: Setup / Implementation | C76: One-time work to configure the agency correctly before go-live. | D76: Plan-tiered one-time implementation fees covering environment setup, role configuration, basic integrations assistance, and go-live prep. Vertical sheets have their own implementation bands. Do not under-scope multi-site or multi-CAD work into Essential setup numbers. | E76: All paying agencies | F76: Put setup on every quote. Expand when discovery finds complexity. | G76: Not ongoing support; not onsite travel (bill travel separately) | H76: Essential–Enterprise / vertical sheets
A77: Services & Commercial | B77: Onsite Deployment Services | C77: Experts in the room for discovery, go-live, and floor support. | D77: Day-rate style onsite packages: discovery visit, installation support, pilot launch, production go-live, CAD vendor workshops, dispatcher floor support, executive briefings, AARs. Travel always separate at GSA-aligned policy — never bury travel in a fixed project price without a travel assumption. | E77: Complex rollouts, political go-lives, limited internal IT | F77: Recommend floor support for the first 48 hours of production. Scope travel explicitly. | G77: Not included travel; not unlimited change orders | H77: Onsite Services
A78: Services & Commercial | B78: Training Packages | C78: Protect adoption — train dispatchers, supervisors, and trainers. | D78: Remote and onsite training for admin, dispatcher, and supervisor roles; train-the-trainer and custom materials for Command/Enterprise. Training prevents ‘we bought it but nobody uses it.’ Train-the-Trainer is high-margin and creates champions. | E78: Training officers, agency admins | F78: Always attach training to Professional+ and vertical launches. | G78: Not a college accredited course; refresher is a separate annual SKU | H78: Training
A79: Services & Commercial | B79: Support Packages (Standard → Mission-Critical / Dedicated) | C79: Match support intensity to operational criticality. | D79: Standard is baseline. Priority is included on Professional — be clear when Mission-Critical is the upsell. Dedicated engineer, CSM, and solution architect are for Command/Enterprise and politically sensitive accounts. Mission-Critical recommended for Command, Enterprise, and agencies in active major-incident posture. | E79: Agency admins; executive sponsors on large deals | F79: Don’t oversell Standard on Command deals. Offer CSM when expansion revenue is expected. | G79: Not custom software development hours | H79: Support
A80: Services & Commercial | B80: Storage & Overages / Seat Overages | C80: Overage math when the agency grows past included seats or media limits. | D80: Each plan includes seat bands and media/storage limits. Seat overages (dispatcher vs admin/supervisor) and storage overages are billed monthly when exceeded. Use these to keep base price clean while giving finance a growth path. See Storage Overages and plan sheets. | E80: Agency finance + admins | F80: Model growth seats in Quote Builder. Don’t hide overage rates. | G80: Not unlimited usage at base price | H80: Storage Overages / plan sheets
A81: FREE STRATEGIC OFFERINGS
A82: Free Strategic Offerings | B82: NexCort iQ Community Connect | C82: Permanent free one-zone tip QR for qualifying campus/venue prospects. | D82: Complimentary land-and-expand wedge: one QR code, one physical zone, tips to a designated email. No dispatcher console, analytics, two-way chat, AI, or Clery log. Use to prove reporting adoption, then upsell full tip console, multi-zone QR/NFC, and analytics. Qualifying institutions only — not a general public free tier. | E82: Campus and venue prospects early in the funnel | F82: Always attach a 60–90 day upsell conversation. Track tip volume as the proof. | G82: Not the full Campus/Venue product; not PSAP 911 | H82: Sales enablement (no price sheet)
A83: Free Strategic Offerings | B83: Complimentary Operational Intelligence Report | C83: One-time PDF from 30–60 days of anonymized CAD export — discovery accelerator. | D83: Prospect provides anonymized CAD export (call type, timestamp, duration — no PII). NexCort returns a short operational intelligence PDF (volume by hour, mix, language share, peaks). Limited availability — treat as a discovery accelerator for PSAP directors/IT sponsors, not a standing freebie on every deal. | E83: PSAP directors and IT sponsors pre-pilot | F83: Trade the report for a scheduled discovery workshop. | G83: Not a continuous BI subscription; not identified caller analytics | H83: Sales enablement (no price sheet)
A84: Free Strategic Offerings | B84: NexCort iQ Wellness | C84: Anonymous end-of-shift check-in for dispatchers — aggregate only for supervisors. | D84: Permanent free wellness check-in for accredited PSAPs. Supervisors see aggregate trends only — never individual responses, call data, or transcripts. No CJIS exposure. Position as workforce retention / duty-of-care goodwill that builds relationship without requiring a full platform purchase. | E84: PSAP directors and wellness/peer-support champions | F84: Offer alongside Professional conversations as culture signal — not as a discount lever on paid SKUs. | G84: Not clinical mental health care; not individual surveillance of dispatchers | H84: Sales enablement (no price sheet)
A85: INTERNAL — DO NOT SELL
A86: Internal — Do Not Sell | B86: NexiQ Sales & RFP Intelligence | C86: Internal PSAP/RFP signal tool for NexCort sales teams only. | D86: Internal sales-intelligence workspace for NexCort sales contractors and RC operators (RFP/PSAP signals, enrichment, scoring). Not an agency-facing SKU. Do not present it in customer proposals or imply agencies are buying ‘NexiQ intelligence’ as a product. | E86: NexCort internal sales only | F86: Never quote to a customer. Keep inside sales portal / RC Admin allowlists. | G86: Not a customer deliverable | H86: Internal only
A87: ⚠ INTERNAL USE ONLY — Sales language for enablement. Do not paste wholesale into public RFP responses without review. CAD write-back stays fail-closed. NexIQ Vision™ / Call Assist / Vault / mesh are never free. Do not sell NexiQ Sales & RFP Intelligence to agencies. Source alignment: addon-catalog + sales-feature-catalog + pricing sheets (Oct 2026).

Sheet Essential
A1: NEXCORT IQ — INTERNAL PRICING GUIDE
A2: NEXCORT IQ ESSENTIAL
A3: Small municipalities · Single-site PSAPs · Pilot deployments · Up to 10 dispatcher seats
A5: BASE SUBSCRIPTION FEES
A6: Item | B6: Tier 1 Micro | C6: Tier 2 Small | D6: Tier 3 Medium | E6: Tier 4 Large | F6: Range (docx) | G6: Notes
A7: Seats | B7: 1–3 | C7: 4–6 | D7: 7–8 | E7: 9–10 | F7: 1–10
A8: Call Volume / Month | B8: <2,000 | C8: 2K–3.5K | D8: 3.5K–4.5K | E8: 4.5K–5K | F8: Varies
A9: Monthly Fee | B9: 2800 | C9: 4200 | D9: 5400 | E9: 6000 | F9: $3,500–$7,500 | G9: Inputs in blue
A10: Annual Fee | B10: =IFERROR(B8*12,"—") | C10: =IFERROR(C8*12,"—") | D10: =IFERROR(D8*12,"—") | E10: =IFERROR(E8*12,"—") | F10: $42K–$90K | G10: Auto-calculated
A11: Recommended Pilot (90-day) | B11: 25000 | C11: 30000 | D11: 37500 | E11: 50000 | F11: $25K–$50K
A12: Setup / Implementation | B12: 10000 | C12: 15000 | D12: 20000 | E12: 25000 | F12: $10K–$25K | G12: One-time
A14: SEAT OVERAGE PRICING
A15: Seat Type | B15: Included in Base | C15: Overage Rate / Month | D15: Notes
A16: Dispatcher Seats | B16: Up to 10 | C16: $150 / seat / month | D16: Seats 11+
A17: Admin / Supervisor Seats | B17: Up to 3 | C17: $100 / seat / month | D17: Seats 4+
A19: INCLUDED CAPABILITIES
A20: Capability | B20: Included? | C20: Notes
A21: Web Application Access | B21: Yes
A22: Desktop Application Access | B22: Yes | C22: Windows & Mac
A23: Role-Based Access Control (RBAC) | B23: Yes
A24: Agency Admin Console | B24: Yes
A25: Core Reporting | B25: Yes
A26: Audit Logs | B26: Yes | C26: CJIS-aware retention
A27: AI-Assisted Intake | B27: Yes
A28: Live Transcription | B28: Yes
A29: Call Triage Workflows | B29: Yes
A30: Call / Session History | B30: Yes
A31: Active Incident View | B31: Yes
A32: Dispatcher Console | B32: Limited | C32: Full in Professional+
A33: Multilingual Intake | B33: Limited | C33: Upgrade for full translation
A34: Language Auto-Detection | B34: Limited
A35: QA Review Tools | B35: Limited | C35: Upgrade for full QA suite
A36: Incident Timeline Reconstruction | B36: Limited
A37: Standard Onboarding | B37: Yes
A38: Integration Assistance | B38: Limited
A40: ESSENTIAL ADD-ON CANDIDATES
A41: Add-On | B41: Price Low / Month | C41: Price High / Month | D41: Notes
A42: Live Translation | B42: 1000 | C42: 3000
A43: Text-to-Voice Support | B43: 750 | C43: 2500
A44: Caller Photo Upload | B44: 500 | C44: 1500
A45: Caller Video Upload | B45: 1000 | C45: 3500
A46: Live Caller Media Streaming | B46: 2500 | C46: 7500 | D46: WebRTC
A47: Media Audit Trail | B47: 750 | C47: 2000
A48: Scorecards | B48: 500 | C48: 1500
A49: Coaching Notes | B49: 500 | C49: 1500
A50: Team Dashboards | B50: 750 | C50: 2500
A51: Priority Support | B51: 1000 | C51: 3000
A52: Dedicated Rollout Planning | B52: 2500 | C52: 7500 | D52: One-time
A54: SALES POSITIONING — Essential Plan
A55: Low-risk entry point — helps agencies modernize without replacing CAD or committing to full transformation.
A56: Best for grant-funded pilots and first-reference customer opportunities.
A57: Position as: "AI-assisted intake and dispatch support that works alongside your existing CAD system."
A58: ⚠ INTERNAL USE ONLY — Public-facing: "Tailored deployment · Custom quote · Contact sales"

Sheet Professional
A1: NEXCORT IQ — INTERNAL PRICING GUIDE
A2: NEXCORT IQ PROFESSIONAL
A3: Growing counties & cities · Full features · Translation · QA · Analytics · Up to 25 dispatcher seats
A5: BASE SUBSCRIPTION FEES
A6: Item | B6: Small Pro T1 | C6: Medium Pro T2 | D6: Large Pro T3 | E6: Max Pro T4 | F6: Range (docx) | G6: Notes
A7: Seats | B7: 1–10 | C7: 11–18 | D7: 19–23 | E7: 24–25 | F7: 1–25
A8: Call Volume / Month | B8: <10,000 | C8: 10K–18K | D8: 18K–23K | E8: 23K–25K | F8: Varies
A9: Monthly Fee | B9: 8500 | C9: 13000 | D9: 15500 | E9: 18000 | F9: $8,500–$18,000
A10: Annual Fee | B10: =IFERROR(B8*12,"—") | C10: =IFERROR(C8*12,"—") | D10: =IFERROR(D8*12,"—") | E10: =IFERROR(E8*12,"—") | F10: $102K–$216K | G10: Auto-calculated
A11: Recommended Pilot (90-day) | B11: 50000 | C11: 70000 | D11: 87500 | E11: 100000 | F11: $50K–$100K
A12: Setup / Implementation | B12: 25000 | C12: 40000 | D12: 50000 | E12: 60000 | F12: $25K–$60K | G12: One-time
A14: SEAT OVERAGE PRICING
A15: Seat Type | B15: Included in Base | C15: Overage Rate / Month | D15: Notes
A16: Dispatcher Seats | B16: Up to 25 | C16: $125 / seat / month | D16: Seats 26+
A17: Admin / Supervisor Seats | B17: Up to 8 | C17: $100 / seat / month | D17: Seats 9+
A19: INCLUDED CAPABILITIES (ALL ESSENTIAL + THESE)
A20: Capability | B20: Included? | C20: Notes
A21: Full Dispatcher Monitoring Console | B21: Yes
A22: Channel / Talk Group Monitoring | B22: Yes
A23: Non-Emergency Intake Queue | B23: Yes
A24: Backlog and SLA Tracking | B24: Yes
A25: Live Translation | B25: Yes | C25: Included — not add-on
A26: Text-to-Voice Support | B26: Yes
A27: Language Auto-Detection | B27: Yes
A28: Caller Photo Upload | B28: Yes
A29: Caller Video Upload | B29: Yes
A30: Media Audit Trail | B30: Yes
A31: Supervisor QA Tools | B31: Yes
A32: Scorecards | B32: Yes
A33: Coaching Notes | B33: Yes
A34: Team Performance Dashboards | B34: Yes
A35: Call Quality Trends | B35: Yes
A36: Incident Timeline Reconstruction | B36: Yes
A37: Post-Incident Reviews | B37: Yes
A38: Integration Assistance | B38: Yes
A39: Priority Support | B39: Yes | C39: Included
A41: LIMITED / ADD-ON IN PROFESSIONAL
A42: Capability | B42: Status | C42: Price Low / Month | D42: Price High / Month | E42: Notes
A43: Live Caller Media Streaming | B43: Limited | C43: 2500 | D43: 6000 | E43: WebRTC real-time
A44: Runbooks / Playbooks | B44: Limited | C44: 1500 | D44: 4000
A45: Monitoring Integrations | B45: Limited | C45: 1000 | D45: 3500
A46: Premium Onboarding | B46: Limited | C46: 10000 | D46: 25000 | E46: One-time
A47: Dedicated Rollout Planning | B47: Limited | C47: 5000 | D47: 15000 | E47: One-time
A48: Major Incident Management | B48: Add-on | C48: 2500 | D48: 7500
A49: Command Dashboard | B49: Add-on | C49: 2500 | D49: 7500
A50: War Rooms | B50: Add-on | C50: 2000 | D50: 6000
A51: Stakeholder Status Pages | B51: Add-on | C51: 1500 | D51: 5000
A52: Alert Correlation | B52: Add-on | C52: 1500 | D52: 5000
A53: Escalation Engine | B53: Add-on | C53: 1500 | D53: 5000
A54: On-Call Routing | B54: Add-on | C54: 1500 | D54: 5000
A55: SLO Dashboards | B55: Add-on | C55: 1500 | D55: 5000
A56: Reliability Reporting | B56: Add-on | C56: 1500 | D56: 5000
A58: SALES POSITIONING — Professional Plan
A59: Demonstrates value across intake, language support, media, QA, and supervisor visibility.
A60: Best for county pilots and growing regional PSAPs ready to go beyond basic AI triage.
A61: Translation and caller media are included — emphasize cost savings vs. separate vendor solutions.
A62: ⚠ INTERNAL USE ONLY

Sheet Command
A1: NEXCORT IQ — INTERNAL PRICING GUIDE
A2: NEXCORT IQ COMMAND
A3: Large agencies · Regional command environments · Major incident coordination · Up to 75 dispatcher seats
A5: BASE SUBSCRIPTION FEES
A6: Item | B6: Small Cmd T1 | C6: Medium Cmd T2 | D6: Large Cmd T3 | E6: Max Cmd T4 | F6: Range (docx) | G6: Notes
A7: Seats | B7: 1–25 | C7: 26–50 | D7: 51–65 | E7: 66–75 | F7: 1–75
A8: Call Volume / Month | B8: <30,000 | C8: 30K–60K | D8: 60K–85K | E8: 85K–100K | F8: Varies
A9: Monthly Fee | B9: 22500 | C9: 31000 | D9: 40000 | E9: 50000 | F9: $22,500–$50,000
A10: Annual Fee | B10: =IFERROR(B8*12,"—") | C10: =IFERROR(C8*12,"—") | D10: =IFERROR(D8*12,"—") | E10: =IFERROR(E8*12,"—") | F10: $270K–$600K | G10: Auto-calculated
A11: Recommended Pilot (90–180 days) | B11: 100000 | C11: 150000 | D11: 200000 | E11: 250000 | F11: $100K–$250K | G11: 6-month standard
A12: Setup / Implementation | B12: 75000 | C12: 100000 | D12: 125000 | E12: 150000 | F12: $75K–$150K | G12: One-time
A14: SEAT OVERAGE PRICING
A15: Seat Type | B15: Included | C15: Overage Rate / Month | D15: Notes
A16: Dispatcher Seats | B16: Up to 75 | C16: $100 / seat / month | D16: Seats 76+
A17: Admin / Supervisor / Command Seats | B17: Up to 20 | C17: $85 / seat / month | D17: Seats 21+
A19: INCLUDED CAPABILITIES (ALL PROFESSIONAL + THESE)
A20: Capability | B20: Included? | C20: Notes
A21: Major Incident Management | B21: Yes
A22: Command Dashboard | B22: Yes
A23: War Rooms | B23: Yes
A24: Runbooks / Playbooks | B24: Yes
A25: Post-Incident Review Tools | B25: Yes
A26: Stakeholder Status Pages | B26: Yes
A27: Monitoring Integrations | B27: Yes
A28: Alert Correlation | B28: Yes
A29: Escalation Engine | B29: Yes
A30: On-Call Routing | B30: Yes
A31: SLO Dashboards | B31: Yes
A32: Reliability Reporting | B32: Yes
... A34: Dedicated Rollout Planning | B34: Yes
A36: LIMITED / ADD-ON IN COMMAND
A37: Capability | B37: Status | C37: Price Low | D37: Price High | E37: Type | F37: Notes
A38: Multi-Site Deployment Support | B38: Limited | C38: 25000 | D38: 100000 | E38: One-time
A39: Custom Security / Compliance Review | B39: Limited | C39: 15000 | D39: 75000 | E39: One-time
A40: Custom CAD Connector | B40: Add-on | C40: 50000 | D40: 250000 | E40: One-time
A41: Dedicated Support Engineer | B41: Add-on | C41: 8000 | D41: 20000 | E41: / month
A42: Onsite Quarterly Review | B42: Add-on | C42: 7500 | D42: 20000 | E42: Per visit
A43: Advanced Data Retention Architecture | B43: Add-on | C43: 10000 | D43: 75000 | E43: One-time
A45: SALES POSITIONING — Command Plan
A46: Best for proving value during high-complexity incidents and cross-team response.
A47: Positions NexCort iQ as a command and coordination platform, not just a dispatcher tool.
A48: Emphasize: war rooms, runbooks, and command dashboards for supervisors and leadership.
A49: ⚠ INTERNAL USE ONLY

Sheet Enterprise
A1: NEXCORT IQ — INTERNAL PRICING GUIDE
A2: ENTERPRISE / STATEWIDE
A3: Multi-agency · 50–500+ seats · Statewide programs · Custom architecture · Dedicated infrastructure
A5: BASE SUBSCRIPTION FEES
A6: Deployment Size | B6: Agencies | C6: Seats | D6: Monthly Fee Range | E6: Annual Fee Range | F6: Notes
A7: Small Enterprise | B7: 2–5 | C7: 50–150 | D7: $60K–$100K / month | E7: $720K–$1.2M / year
A8: Medium Enterprise | B8: 6–15 | C8: 150–300 | D8: $100K–$175K / month | E8: $1.2M–$2.1M / year
A9: Large Enterprise | B9: 16–30 | C9: 300–500 | D9: $175K–$250K / month | E9: $2.1M–$3M / year
A10: Statewide | B10: 30+ | C10: 500+ | D10: $250K+ / month | E10: $3M–$10M+ / year | F10: Custom contract
A12: SEAT OVERAGE
A13: Seat Type | B13: Overage Rate | C13: Notes
A14: Dispatcher Seats | B14: $75–$100 / seat / month | C14: Negotiated per contract
A15: Admin / Supervisor Seats | B15: Custom | C15: Per SOW
A17: SETUP & IMPLEMENTATION
A18: Item | B18: Low | C18: High | D18: Notes
A19: Setup / Implementation | B19: 20000 | C19: 75000 | D19: Per SOW — wide range
A20: Multi-Site Deployment Support | B20: 25000 | C20: 100000 | D20: One-time per scope
A21: Custom Security / Compliance Review | B21: 15000 | C21: 75000 | D21: One-time
A22: Advanced Rollout Services | B22: Custom | C22: Custom | D22: SOW required
A24: INCLUDED CAPABILITIES
A25: Capability | B25: Included? | C25: Notes
A26: All Command capabilities (as applicable) | B26: Yes
A27: Multi-Agency Architecture | B27: Yes
A28: Multi-Site Deployment Planning | B28: Yes
A29: Custom Integrations | B29: Yes | C29: Per SOW
A30: Custom Retention / Security Options | B30: Yes
A31: Advanced Rollout Services | B31: Yes
A32: Procurement and Compliance Support | B32: Yes
A33: Tailored Deployment Architecture | B33: Yes
A34: Dedicated Architecture Planning | B34: Yes
A35: Executive Reporting | B35: Yes
A36: Custom SOW | B36: Yes
A38: SALES POSITIONING — Enterprise / Statewide
A39: Best sales angle: NexCort iQ becomes a long-term public safety modernization platform.
A40: Strong fit for grant-funded programs, large procurements, and regional emergency management transformation.
A41: Every Enterprise deal requires a custom SOW — do not quote fixed prices without Sales Director sign-off.
A42: ⚠ INTERNAL USE ONLY — Enterprise pricing requires VP Sales + Sales Director approval before quoting.

Sheet CAD Integration
A1: NEXCORT IQ — INTERNAL PRICING GUIDE
A2: CAD INTEGRATION ADD-ONS
A3: One-time fees · Complexity-tiered · NexCort iQ enhances CAD — it does not replace it
A5: DISCOVERY & PLANNING
A6: Service | B6: Price Low | C6: Price High | D6: Notes
A7: Basic CAD Discovery Workshop | B7: 7500 | C7: 7500 | D7: Single CAD, standard environment
A8: Standard CAD Discovery Workshop | B8: 10000 | C8: 10000 | D8: Recommended starting point
A9: Advanced CAD Discovery Workshop | B9: 15000 | C9: 15000 | D9: Complex multi-CAD environments
A10: CAD Field Mapping Document | B10: 7500 | C10: 20000
A11: CAD Integration Audit Logging Package | B11: 10000 | C11: 35000
A12: CAD Rollback and Failover Planning | B12: 10000 | C12: 30000
A14: CAD VENDOR COORDINATION
A15: Tier | B15: Price | C15: Description
A16: Basic Vendor Coordination | B16: 8000 | C16: Single CAD vendor, standard API
A17: Standard Vendor Coordination | B17: 11000 | C17: Moderate complexity
A18: Premium Vendor Coordination | B18: 16000 | C18: Multi-vendor or legacy CAD
A19: CAD Sandbox Testing Package | B19: 6000 | C19: Included or $15K–$50K depending on scope
A21: READ-ONLY INTEGRATION
A22: Complexity Tier | B22: One-Time Fee | C22: Description
A23: Tier 1 — Simple | B23: 10000 | C23: Standard REST or webhook
A24: Tier 2 — Standard | B24: 18500 | C24: Moderate mapping / transform
A25: Tier 3 — Complex | B25: 23425 | C25: Legacy protocol / custom adapter
A26: Tier 4 — Advanced | B26: 36450 | C26: Multi-system / real-time
A28: ASSISTED WRITE-BACK INTEGRATION
A29: Complexity Tier | B29: One-Time Fee | C29: Description
A30: Tier 1 — Simple | B30: 28500 | C30: Basic write-back with confirmation
A31: Tier 2 — Standard | B31: 34250 | C31: Standard bidirectional
A32: Tier 3 — Complex | B32: 44000 | C32: Complex data mapping
A33: Tier 4 — Advanced | B33: 51600 | C33: Full bidirectional + validation
A35: AUTOMATED WRITE-BACK INTEGRATION
A36: Complexity Tier | B36: One-Time Fee | C36: Description
A37: Tier 1 — Simple | B37: 46000 | C37: Automated rules-based write-back
A38: Tier 2 — Standard | B38: 58000 | C38: Full automation with logging
A39: Tier 3 — Complex | B39: 67000 | C39: Complex event-driven automation
A40: Tier 4 — Advanced | B40: 74000 | C40: Custom AI-assisted write-back
A42: ADDITIONAL CAD CONNECTORS
A43: Item | B43: Low | C43: High | D43: Notes
A44: Additional CAD Vendor Connector | B44: 75000 | C44: 150000 | D44: Per connector — one-time
A46: RULE: Do NOT include full CAD write-back in pilot base pricing. Scope separately after discovery, sandbox testing, and vendor validation.
A47: Annual maintenance on integrations: 15–20% of integration fee, billed separately.

Sheet Caller Media
A1: NEXCORT IQ — INTERNAL PRICING GUIDE
A2: CALLER TEXT, PHOTO & VIDEO ADD-ONS
A3: SMS links · Photo upload · Video upload · Live streaming · Redaction · Evidence retention
A5: SMS & TEXT
A6: Service | B6: Monthly Fee Low | C6: Monthly Fee High | D6: Notes
A7: Caller SMS Link Generation | B7: 1500 | C7: 5000
A8: Text-Only Emergency Conversation Link | B8: 2000 | C8: 7500 | D8: Async text triage
A10: PHOTO UPLOAD
A11: Tier | B11: Monthly Fee Low | C11: Monthly Fee High | D11: Notes
A12: Basic (<500 photos/mo, 5MB, 30-day retention) | B12: 1000 | C12: 3500
A13: Standard (<2K photos/mo, 10MB, 90-day retention) | B13: 1000 | C13: 3500
A14: Premium (5K+ photos/mo, 25MB, 1-year retention) | B14: 2000 | C14: 4000
A16: VIDEO UPLOAD & LIVE STREAMING
A17: Service | B17: Monthly Fee Low | C17: Monthly Fee High | D17: Notes
A18: Caller Video Upload | B18: 2500 | C18: 8500 | D18: Async upload
A19: Live Caller Video Streaming | B19: 5000 | C19: 20000 | D19: WebRTC · real-time
A20: Media Audit Trail | B20: 1500 | C20: 5000 | D20: Chain-of-custody logging
A21: Evidence Retention Controls | B21: 2500 | C21: 10000
A22: Secure Media Storage Package | B22: 1500 | C22: 7500 | D22: Plus storage overages
A23: Media Redaction Workflow | B23: 5000 | C23: 20000 | D23: High-margin — scope carefully
A24: Large-Volume Media Package | B24: Custom | C24: Custom | D24: Custom quote required
A26: SALES POSITIONING — Caller Media Add-Ons
A27: Gives dispatchers more real-time context before responders arrive.
A28: Useful when callers cannot safely speak or when visual context improves situational awareness.
A29: Supports better documentation through audit trails and evidence retention.
A30: ⚠ INTERNAL USE ONLY

Sheet Supervisor QA
A1: NEXCORT IQ — INTERNAL PRICING GUIDE
A2: SUPERVISOR & QA ADD-ONS
A3: Scorecards · Coaching · Dashboards · QA rubrics · Analytics · AI grading
A5: QA & COACHING MODULES
A6: Module | B6: Monthly Fee Low | C6: Monthly Fee High | D6: Notes
A7: QA Review Tools | B7: 1500 | C7: 5000 | D7: Full suite — replaces Limited in Essential
A8: Dispatcher Scorecards | B8: 1000 | C8: 4000 | D8: Per-call scoring templates
A9: Coaching Notes | B9: 1000 | C9: 4000 | D9: Supervisor annotation layer
A10: Team Performance Dashboards | B10: 2000 | C10: 7500 | D10: Real-time supervisor view
A11: Call Quality Trends | B11: 2000 | C11: 7500 | D11: Trend reporting + export
A12: Supervisor Training Dashboard | B12: 2500 | C12: 10000
A13: AI QA Scoring Model | B13: 2500 | C13: 10000 | D13: AI-assisted grading
A14: Monthly QA Analytics Report | B14: 2500 | C14: 7500
A16: CUSTOM QA DEVELOPMENT
A17: Item | B17: Price Low | C17: Price High | D17: Type | E17: Notes
A18: Custom QA Scoring Rubric | B18: 7500 | C18: 25000 | D18: One-time
A20: BUNDLE: Scorecards + Coaching Notes + Team Dashboards — 15% discount when ordered together.
A21: SALES POSITIONING — Supervisor & QA Add-Ons
A22: Helps supervisors identify training gaps and improve consistency.
A23: Useful for agencies focused on compliance, coaching, and continuous improvement.
A24: Custom QA rubric is a high-value one-time add-on — scope after pilot.
A25: ⚠ INTERNAL USE ONLY

Sheet Transcription
A1: NEXCORT IQ — INTERNAL PRICING GUIDE
A2: TRANSCRIPTION & TRANSLATION ADD-ONS
A3: Enhanced accuracy · Speaker diarization · Live translation · Language packs · Text-to-voice
A5: ENHANCED TRANSCRIPTION ACCURACY
A6: Volume Tier | B6: Monthly Fee | C6: Notes
A7: Tier 1 (<5K calls/month) | B7: 1500
A8: Tier 2 (5K–15K calls/month) | B8: 3000
A9: Tier 3 (15K+ calls/month) | B9: 5000
A11: SPEAKER SEPARATION (DIARIZATION)
A12: Volume Tier | B12: Monthly Fee | C12: Notes
A13: Tier 1 (<5K calls/month) | B13: 1000
A14: Tier 2 (5K–15K calls/month) | B14: 2500
A15: Tier 3 (15K+ calls/month) | B15: 4000
A17: LIVE TRANSLATION
A18: Tier | B18: Languages / Volume | C18: Monthly Fee | D18: Notes
A19: Tier 1 | B19: 2–3 languages, <2K translations/mo | C19: 2500
A20: Tier 2 | B20: 4–6 languages, 2K–5K translations/mo | C20: 5500
A21: Tier 3 | B21: 7–10 languages, 5K–10K translations/mo | C21: 8000
A22: Tier 4 | B22: 10+ languages, 10K+ translations/mo | C22: 10000 | D22: Custom SLA available
A24: LANGUAGE PACKS & ADDITIONAL SERVICES
A25: Item | B25: Monthly Fee Low | C25: Monthly Fee High | D25: Notes
A26: Multilingual Intake Package | B26: 1500 | C26: 5000
A27: Text-to-Voice Support | B27: 1500 | C27: 5000
A28: Top 10 Language Support Package | B28: 3500 | C28: 12500 | D28: Bundled
A29: Top 15 Language Support Package | B29: 5000 | C29: 18000 | D29: Bundled
A30: Custom Language Package | B30: 1000 | C30: 4000 | D30: Per language / month
A31: Translation Audit Trail | B31: 1000 | C31: 4000
A33: SALES POSITIONING — Transcription & Translation Add-Ons
A34: Supports diverse communities and improves language access during intake.
A35: Helps dispatchers understand callers faster and create more complete incident records.
A36: Live translation is included in Professional+ — upsell language packs for depth.
A37: ⚠ INTERNAL USE ONLY

Sheet Incident Command
A1: NEXCORT IQ — INTERNAL PRICING GUIDE
A2: INCIDENT COMMAND & COLLABORATION ADD-ONS
A3: War rooms · Command dashboards · Runbooks · Timelines · Stakeholder pages · EOC support
A5: INCIDENT COMMAND ADD-ONS
A6: Module | B6: Monthly Fee Low | C6: Monthly Fee High | D6: Notes
A7: Major Incident Management | B7: 5000 | C7: 20000 | D7: Included in Command plan
A8: Command Dashboard | B8: 5000 | C8: 20000 | D8: Included in Command plan
A9: War Rooms | B9: 3500 | C9: 15000 | D9: Included in Command plan
A10: Runbooks / Playbooks | B10: 2500 | C10: 12500 | D10: Included in Command plan
A11: Incident Timeline Reconstruction | B11: 2500 | C11: 10000
A12: Post-Incident Reviews | B12: 2500 | C12: 10000
A13: Stakeholder Status Pages | B13: 3500 | C13: 15000
A14: Public Information Officer View | B14: 2500 | C14: 10000
A15: Executive Incident Briefing Module | B15: 3500 | C15: 15000
A17: SALES POSITIONING — Incident Command Add-Ons
A18: Moves agencies from scattered communication to structured incident coordination.
A19: Valuable during storms, active incidents, large events, mutual aid, and EOC activity.
A20: Note: Major incident management and command dashboard are included in Command plan — upsell for Professional agencies.
A21: ⚠ INTERNAL USE ONLY

Sheet Reliability Ops
A1: NEXCORT IQ — INTERNAL PRICING GUIDE
A2: RELIABILITY & TECHNICAL OPERATIONS ADD-ONS
A3: Monitoring · Alert correlation · Escalation · On-call routing · SLOs · CloudWatch
A5: RELIABILITY & MONITORING ADD-ONS
A6: Module | B6: Monthly Fee Low | C6: Monthly Fee High | D6: Notes
A7: Monitoring Integrations | B7: 2500 | C7: 10000 | D7: Included in Command plan
A8: Alert Correlation | B8: 2500 | C8: 10000
A9: Escalation Engine | B9: 2500 | C9: 10000
A10: On-Call Routing | B10: 2500 | C10: 10000
A11: SLO Dashboards | B11: 2000 | C11: 7500
A12: Reliability Reporting | B12: 2000 | C12: 7500
A13: 24/7 Incident Support Upgrade | B13: 7500 | C13: 25000
A15: ONE-TIME RELIABILITY SERVICES
A16: Item | B16: Price Low | C16: Price High | D16: Type | E16: Notes
A17: CloudWatch Dashboard Package | B17: 5000 | C17: 20000 | D17: One-time
A18: Agency-Specific Monitoring Connector | B18: 10000 | C18: 50000 | D18: One-time
A20: SALES POSITIONING — Reliability & Tech Ops Add-Ons
A21: Gives agencies confidence in system uptime and accountability.
A22: Supports technical transparency during mission-critical operations.
A23: Position for agencies with existing NOC/SOC or formal on-call processes.
A24: ⚠ INTERNAL USE ONLY

Sheet Onsite Services
A1: NEXCORT IQ — INTERNAL PRICING GUIDE
A2: ONSITE DEPLOYMENT SERVICES
A3: Discovery · Installation · Go-live support · Floor support · Travel policy
A5: ONSITE SERVICE RATES
A6: Service | B6: Price Low | C6: Price High | D6: Plus Travel? | E6: Notes
A7: Onsite Discovery Visit | B7: 7500 | C7: 15000 | D7: Yes
A8: Onsite Installation Support | B8: 15000 | C8: 35000 | D8: Yes
A9: Onsite Pilot Launch Support | B9: 20000 | C9: 50000 | D9: Yes
A10: Onsite Production Go-Live Support | B10: 35000 | C10: 100000 | D10: Yes | E10: High-value, plan carefully
A11: Onsite CAD / Vendor Integration Workshop | B11: 15000 | C11: 50000 | D11: Yes
A12: Onsite Dispatcher Floor Support | B12: 10000 | C12: 25000 | D12: Yes | E12: Per week
A13: Onsite Executive Briefing | B13: 7500 | C13: 20000 | D13: Yes
A14: Onsite After-Action Review | B14: 10000 | C14: 30000 | D14: Yes
A16: TRAVEL POLICY
A17: Travel Item | B17: Policy | C17: Notes
A18: Airfare | B18: Actual cost | C18: Economy unless >3 hrs
A19: Hotel | B19: Actual cost
A20: Rental Car / Rideshare | B20: Actual cost
A21: Meals / Per Diem | B21: Federal GSA rate or actual | C21: Whichever is lower
A22: Travel Admin Fee | B22: Optional 10% markup | C22: Must be agreed in SOW
A23: Minimum Onsite Billing | B23: 2 days | C23: Applies to all onsite work
A25: SALES POSITIONING — Onsite Services
A26: Reduces rollout risk by putting NexCort iQ experts with agency staff.
A27: Especially valuable for complex workflows, multiple stakeholders, or limited internal IT.
A28: Always scope travel separately — never bundle into a fixed project price without a travel cap clause.
A29: ⚠ INTERNAL USE ONLY

Sheet Training
A1: NEXCORT IQ — INTERNAL PRICING GUIDE
A2: TRAINING PRICING
A3: Remote & onsite · Dispatcher · Supervisor · Admin · Train-the-trainer · Custom
A5: REMOTE TRAINING
A6: Package | B6: Price Low | C6: Price High | D6: Notes
A7: Standard Onboarding | B7: Included | C7: Included | D7: Included in all plans
A8: Remote Admin Training | B8: 2500 | C8: 7500 | D8: Per session
A9: Remote Dispatcher Training | B9: 2500 | C9: 10000 | D9: Per session
A10: Remote Supervisor Training | B10: 3500 | C10: 12500 | D10: Per session
A12: ONSITE TRAINING (plus travel)
A13: Package | B13: Price Low | C13: Price High | D13: Plus Travel? | E13: Notes
A14: Onsite Dispatcher Training | B14: 10000 | C14: 30000 | D14: Yes
A15: Onsite Supervisor Training | B15: 10000 | C15: 30000 | D15: Yes
A17: ADVANCED TRAINING PACKAGES
A18: Package | B18: Price Low | C18: Price High | D18: Notes
A19: Train-the-Trainer Package | B19: 15000 | C19: 50000
A20: Custom Training Materials | B20: 5000 | C20: 20000 | D20: One-time development fee
A21: Annual Refresher Training | B21: 10000 | C21: 50000 | D21: Per year
A23: SALES POSITIONING — Training Pricing
A24: Training protects the agency from workflow confusion and reduces support burden.
A25: Helps teams understand what NexCort iQ does vs. CAD, CPE, SOPs, and AI decision support.
A26: Train-the-Trainer is high-margin and creates internal champions — recommend for Command+.
A27: ⚠ INTERNAL USE ONLY
A29: VENUE / CONVENTION SECURITY TRAINING (aligned RFP 2396IP)
A30: Package | B30: Price Low | C30: Price High | D30: Notes
A31: Venue Security end-user training (virtual) | B31: 1500 | C31: 1500 | D31: Per session · up to 20 · 2 hrs · RFP 2396IP optional rate
A32: Venue Security administrator training (virtual) | B32: 2000 | C32: 2000 | D32: Per session · up to 5 admins · 3 hrs · RFP 2396IP optional rate
A33: Venue Security training package (4 sessions) | B33: 3000 | C33: 3000 | D33: 2 end-user + 2 admin · included in Security Dept impl package

Sheet Support
A1: NEXCORT IQ — INTERNAL PRICING GUIDE
A2: SUPPORT PACKAGES
A3: Standard · Priority · Mission-Critical · Dedicated
A5: SUPPORT TIERS OVERVIEW
A6: Support Tier | B6: User Range | C6: Monthly Fee | D6: Response SLA | E6: Key Features | F6: Notes
A7: Standard Support | B7: All plans | C7: Included | D7: Business hours | E7: Email + KB + onboarding | F7: Included in base
A8: Priority Support — Small | B8: <25 users | C8: $2,500/mo | D8: 4-hour response | E8: Named contact + monthly review
A9: Priority Support — Medium | B9: 25–75 users | C9: $5,000/mo | D9: 4-hour response | E9: Named contact + monthly review
A10: Priority Support — Large | B10: 75+ users | C10: $7,500/mo | D10: 2-hour response | E10: Named contact + monthly review
A11: Mission-Critical Support | B11: Command+ | C11: Custom | D11: 1-hour response | E11: 24/7 · escalation handling · exec reviews | F11: Recommended for Command+
A13: DEDICATED SUPPORT RESOURCES
A14: Resource | B14: Monthly Fee Low | C14: Monthly Fee High | D14: Notes
A15: Dedicated Support Engineer | B15: 8000 | C15: 20000 | D15: Named engineer, SLA-bound
A16: Customer Success Manager (CSM) | B16: Custom | C16: Custom | D16: Enterprise / statewide accounts
A17: Dedicated Solution Architect | B17: Custom | C17: Custom | D17: Complex integration programs
A18: Dedicated 24/7 Support Team | B18: Custom | C18: Custom | D18: Per contract
A20: SALES POSITIONING — Support Packages
A21: Mission-Critical support recommended for Command, Enterprise, and any agency in active production.
A22: Dedicated support turns NexCort iQ from a software vendor into an operational partner.
A23: Priority support is included in Professional — be clear that Mission-Critical is an upgrade.
A24: ⚠ INTERNAL USE ONLY
A26: VENUE / CONVENTION — EXTENDED BUSINESS HOURS (RFP 2396IP)
A27: Support Tier | B27: User Range | C27: Fee | D27: Response SLA | E27: Key Features | F27: Notes
A28: Extended Business Hours Support | B28: Venue Security Dept (<25 users) | C28: $7,200/yr ($600/mo) | D28: P1: 1-hour · P2: 4-hour | E28: 8 AM–8 PM ET Mon–Fri · weekend email ack 4-hr · patches | F28: List rate used on RFP 2396IP — between Standard (included) and Priority ($2,500/mo)

Sheet Storage Overages
A1: NEXCORT IQ — INTERNAL PRICING GUIDE
A2: STORAGE, USAGE & OVERAGES
A3: Included limits by plan · Per-unit overage rates · Call volume · Transcription · Media
A5: INCLUDED USAGE BY PLAN
A6: Resource | B6: Essential | C6: Professional | D6: Command | E6: Enterprise | F6: Notes
A7: Storage | B7: 100 GB | C7: 500 GB | D7: 2 TB | E7: Custom | F7: Expandable via add-on
A8: Call Recording Retention | B8: 90 days | C8: 180 days | D8: 1 year | E8: Custom
A9: Transcription Volume | B9: Included | C9: Included | D9: Included | E9: Custom | F9: Volume limits per contract
A10: Translation Requests | B10: Limited | C10: Included | D10: Included | E10: Custom
A11: API Calls / Month | B11: Standard | C11: Standard | D11: High | E11: Custom
A12: Media Storage (photos/video) | B12: Limited | C12: Standard | D12: Enhanced | E12: Custom
A14: OVERAGE RATES
A15: Resource | B15: Overage Rate | C15: Unit | D15: Notes
A16: Additional Storage | B16: 0.08 | C16: per GB / month | D16: S3 standard + margin
A17: Additional Call Volume | B17: 0.003 | C17: per call over limit | D17: Blended AI processing cost
A18: Additional Transcription | B18: 0.01 | C18: per minute over limit
A19: Additional Translation Requests | B19: 0.05 | C19: per request over limit
A20: Additional Photo Storage | B20: 0.05 | C20: per 100 photos over limit
A21: Archive Storage | B21: 0.02 | C21: per GB / month | D21: Cold storage tier
A22: Data Export | B22: 0.1 | C22: per GB exported | D22: Large exports only
A23: High-Volume API Use | B23: Custom | C23: Custom | D23: Negotiate in contract
A25: SALES POSITIONING — Storage & Overages
A26: Overages protect both the agency and NexCort iQ by allowing flexible usage without forcing an immediate plan change.
A27: Useful during storms, major incidents, seasonal spikes, or large-scale emergencies.
A28: Always discuss expected call volumes during discovery to right-size the plan before signing.
A29: ⚠ INTERNAL USE ONLY
A31: VENUE SECURITY DEPARTMENT STORAGE (RFP 2396IP)
A32: Item | B32: Rate | C32: Unit | D32: Notes
A33: Included storage package (500 GB + 7-year retention) | B33: $3,600 | C33: per year | D33: Quoted as recurring line on Security Dept deals
A34: Additional storage (Venue Security model) | B34: $300 | C34: per 100 GB / year | D34: Min 100 GB · differs from PSAP $0.08/GB/mo overage

Sheet Pilot Programs
A1: NEXCORT IQ — INTERNAL PRICING GUIDE
A2: PILOT PROGRAMS
A3: Pre-packaged pilot bundles for common agency profiles
A5: PILOT PROGRAM OVERVIEW
A6: Program | B6: Duration | C6: Fee Low | D6: Fee High | E6: Typical Scope | F6: Notes
A7: Small City Pilot | B7: 90 days | C7: 20000 | D7: 40000 | E7: Essential + setup + onboarding + training + CAD discovery | F7: Grant-friendly
A8: County Professional Pilot | B8: 90 days | C8: 50000 | D8: 100000 | E8: Professional + translation + caller media + CAD discovery/read-only + training
A9: Command Center Pilot | B9: 90–180 days | C9: 100000 | D9: 250000 | E9: Command + CAD read-only + major incident + war rooms + onsite + training
A10: Enterprise / Statewide Pilot | B10: 6 months | C10: 250000 | D10: 750000 | E10: Enterprise architecture + multi-site + custom integrations + dedicated support | F10: Custom SOW required
A12: SALES POSITIONING — Small City Pilot
A13: Smaller municipalities that want to evaluate NexCort iQ without a full production commitment.
A14: Usually includes Essential-level access, setup, onboarding, training, and CAD discovery.
A15: Sales angle: low-risk, practical way to test value, collect feedback, and support grant-funded modernization.
A17: SALES POSITIONING — County Professional Pilot
A18: Mid-size cities, counties, or regional PSAPs ready for a broader operational test.
A19: Includes Professional-level features: translation, caller media, QA, and supervisor visibility.
A20: Sales angle: demonstrates value across multiple workflows — not just basic AI triage.
A22: SALES POSITIONING — Command Center Pilot
A23: Larger agencies, EOCs, or regional response environments.
A24: May include Command-level tools, war rooms, onsite support, and expanded training.
A25: Sales angle: proves NexCort iQ as a command and coordination platform.
... A32: ⚠ INTERNAL USE ONLY — Pilot pricing to be approved by Sales Director before quoting.

Sheet Discounting
A1: NEXCORT IQ — INTERNAL PRICING GUIDE
A2: DISCOUNTING RULES
A3: Internal — protect pricing discipline while allowing strategic flexibility
A5: STANDARD DISCOUNT SCHEDULE
A6: Scenario | B6: Max Discount | C6: Approval Required | D6: Notes
A7: Annual commitment (vs month-to-month) | B7: 10% | C7: Account Executive | D7: Standard offer — always available
A8: 2-year commitment | B8: 15% | C8: Account Executive
A9: 3-year commitment | B9: 20% | C9: Sales Director
A10: Pilot-to-production conversion | B10: 10% | C10: Account Executive | D10: First year only
A11: Competitive displacement | B11: 15% | C11: Sales Director | D11: Requires documentation
A12: Government / municipal grant-funded | B12: 10% | C12: Account Executive
A13: Bundle discount (3+ add-ons) | B13: 15% | C13: Account Executive | D13: Auto-applied
A14: Nonprofit / tribal agency | B14: 20% | C14: Sales Director | D14: Case-by-case
A15: Strategic / reference account | B15: 25% | C15: VP of Sales | D15: Board approval if >25%
A17: PROTECTED LINE ITEMS (DO NOT HEAVILY DISCOUNT)
A18: Line Item | B18: Why Protected | C18: Guidance
A19: CAD Integration | B19: Significant labor + vendor coordination | C19: Discount max 5% — scope separately
A20: Custom Development | B20: High labor cost | C20: No standard discount — scope per SOW
A21: Onsite Services | B21: Travel + staff time | C21: Discount travel separately if needed
A22: Dedicated Support | B22: Named resource commitment | C22: No discount — price is the floor
A24: ⚠ Any discount >25% requires VP of Sales + CFO written approval. Never quote below floor without authorization.
A25: RULE: Discounts reward commitment, scale, and strategic value — not just pressure to close.

Sheet RC Campus
A1: NEXCORT IQ — INTERNAL PRICING GUIDE
A2: NEXCORT IQ CAMPUS
A3: Universities · Colleges · K-12 · Campus safety reporting · QR/NFC · Anonymous & identified reporting · Clery documentation
A5: BASE SUBSCRIPTION — PER-STUDENT ANNUAL PRICING
A6: Item | B6: Rate | C6: Notes
A7: Annual Rate | B7: $1.40 per enrolled student / year | C7: Based on total institutional enrollment. 30% non-user adjustment already applied.
A8: Minimum Annual Contract | B8: $15,000 / year | C8: Applies to institutions under ~10,700 enrolled students.
A9: Billing Basis | B9: Total enrollment (census) | C9: Enrollment figure from most recent official institutional census. Not subject to reduction based on platform utilization.
A10: Contract Term | B10: Annual (minimum) | C10: Multi-year terms available. 3-year term: 10% discount with Sales Director approval.
A12: ANNUAL CONTRACT VALUE — REFERENCE TABLE
A13: Institution Type | B13: Enrollment | C13: Annual Contract | D13: Monthly Equivalent | E13: Notes
A14: Community College — Small | B14: 4,000 | C14: $15,000 | D14: $1,250 | E14: Minimum applies
A15: Community College — Large | B15: 18,000 | C15: $25,200 | D15: $2,100
A16: Regional University | B16: 12,000 | C16: $16,800 | D16: $1,400
A17: Mid-Size State School | B17: 28,000 | C17: $39,200 | D17: $3,267
A18: Large State University | B18: 55,000 | C18: $77,000 | D18: $6,417
A19: Flagship University | B19: 48,000 | C19: $67,200 | D19: $5,600
A21: IMPLEMENTATION — ONE-TIME
A22: Enrollment Size | B22: Implementation Fee | C22: Includes
A23: Under 10,000 students | B23: $8,000 | C23: QR configuration · admin training · zone setup · emergency notification integration · Clery walkthrough
A24: 10,001 – 25,000 | B24: $15,000 | C24: All above + extended zone mapping + multi-building configuration
A25: 25,001 – 50,000 | B25: $25,000 | C25: All above + multi-campus configuration + department admin training
A26: 50,001+ | B26: $35,000 | C26: Full enterprise configuration · dedicated rollout support · custom Clery workflow
A28: INCLUDED IN BASE — ALL CAMPUS PLANS
A29: Capability | B29: Included? | C29: Notes
A30: QR-Based Anonymous & Identified Reporting | B30: Yes | C30: No app download required — any smartphone camera
A31: SMS Reporting Channel | B31: Yes | C31: Text-based intake with auto-reply
A32: Two-Way Chat | B32: Yes | C32: Dispatcher ↔ student secure messaging
A33: Photo & Video Evidence Intake | B33: Yes | C33: Attached to incident record automatically
A34: NFC Tag Support | B34: Yes | C34: Same URL as QR code — one-tap reporting
A35: Campus Security Console | B35: Yes | C35: Role-based: campus_security role
A36: Campus Supervisor Dashboard | B36: Yes | C36: Live incident map · active reports · escalations
A37: Campus Admin Console | B37: Yes | C37: User management · zone configuration · reporting
A38: Incident Timeline | B38: Yes | C38: Auto-built event log per incident
A39: Basic Clery Act Documentation Log | B39: Yes | C39: Annual Security Report support
A40: Anonymous Reporting | B40: Yes | C40: No identity stored when anonymous mode selected
... A44: Standard Onboarding | B44: Yes | C44: Remote — included
A46: CAMPUS ADD-ONS
A47: Add-On | B47: Price Low / Year | C47: Price High / Year | D47: Notes
A48: AI Incident Summary | B48: $3,000 | C48: $8,000 | D48: On-demand supervisor AI summary · Cortex AI
A49: Advanced Clery Reporting | B49: $4,000 | C49: $10,000 | D49: Export-ready · audit trail · annual report builder
A50: Zone-Based QR/NFC Reporting | B50: $3,000 | C50: $7,500 | D50: Additional zones beyond standard config
A51: NexCort iQ Connect — Camera Integ. | B51: $5,000 | C51: $15,000 | D51: ONVIF/RTSP/WebRTC camera integration
A52: Two-Way Chat Translation (40+ langs) | B52: $2,500 | C52: $6,000 | D52: Live translation in chat
A53: Analytics Dashboard | B53: $4,000 | C53: $10,000 | D53: Trend reporting · heat maps · Clery trends
A54: Agency Share Feature | B54: $1,500 | C54: $1,500 | D54: Cross-agency incident awareness / month — see Feature Add-Ons sheet
A55: SMS Location Acquisition | B55: $2,500 | C55: $6,000 | D55: Auto-reply location link on text intake
A56: Priority Support | B56: $1,000 | C56: $3,000 | D56: Per month — 4-hr response · named contact
A57: Onsite Training | B57: $10,000 | C57: $25,000 | D57: One-time · plus travel
A59: CONTRACT LANGUAGE NOTE: Fees are calculated on total institutional enrollment from the most recent official enrollment census. Not subject to reduction based on platform utilization rates.
A60: SALES POSITIONING: Position as 'the safety layer every campus already needs.' No app download = zero adoption barrier. QR + NFC + SMS = three reporting channels on one sign. Clery documentation is built in — not bolted on.
A61: ⚠ INTERNAL USE ONLY — Do not share with agencies or prospects without Sales Director approval.

Sheet RC Venue
A1: NEXCORT IQ — INTERNAL PRICING GUIDE
A2: NEXCORT IQ VENUE
A3: Stadiums · Arenas · Convention centers · Concert venues · Fan-to-security communication · QR/NFC · Zone-based reporting
A5: BASE SUBSCRIPTION — CAPACITY-BASED ANNUAL PRICING
A6: Venue Tier | B6: Capacity | C6: Annual Fee | D6: Monthly Equivalent | E6: Typical Venue Types
A7: Tier 1 — Small Venue | B7: Under 5,000 | C7: $18,000 | D7: $1,500 | E7: Community centers · amphitheaters · small arenas
A8: Tier 2 — Mid Venue | B8: 5,000–20,000 | C8: $28,000 | D8: $2,333 | E8: Mid-size arenas · convention halls · fairgrounds
A9: Tier 3 — Large Venue | B9: 20,000–50,000 | C9: $45,000 | D9: $3,750 | E9: Major arenas · ballparks · large concert venues
A10: Tier 4 — Stadium | B10: 50,000+ | C10: $72,000 | D10: $6,000 | E10: NFL/MLB/NBA stadiums · large amphitheaters
A11: Multi-Venue Package | B11: 2+ venues | C11: Custom | D11: Custom | E11: Volume discount — requires Sales Director approval
A13: IMPLEMENTATION — ONE-TIME
A14: Venue Tier | B14: Implementation Fee | C14: Includes
A15: Tier 1 — Small | B15: $10,000 | C15: Zone/section setup · staff training · QR/NFC configuration · security console setup
A16: Tier 2 — Mid | B16: $18,000 | C16: All above + extended zone mapping · multi-gate config · event type workflows
A17: Tier 3 — Large | B17: $28,000 | C17: All above + camera integration planning · multi-section config · command setup
A18: Tier 4 — Stadium | B18: $40,000 | C18: Full enterprise config · dedicated rollout · command integration · event protocols
A20: INCLUDED IN BASE — ALL VENUE PLANS
A21: Capability | B21: Included? | C21: Notes
A22: QR-Based Fan Reporting | B22: Yes | C22: No app download — any smartphone camera
A23: NFC Tag Support | B23: Yes | C23: Tap-to-report on seat backs, concourse signs, restroom entries
A24: SMS Reporting Channel | B24: Yes | C24: Text-based intake
A25: Two-Way Chat — Fan to Security | B25: Yes | C25: Secure messaging
A26: Photo & Video Evidence Intake | B26: Yes | C26: Attached to incident record
A27: Zone / Section / Gate Based Reporting | B27: Yes | C27: Section + gate pre-filled from QR/NFC scan
A28: Venue Security Console | B28: Yes | C28: venue_security role — Signal color system
A29: Venue Supervisor Dashboard | B29: Yes | C29: Live event view · all zones · escalations
A30: Venue Admin Console | B30: Yes | C30: Staff management · event config · zone setup
A31: Incident Timeline | B31: Yes | C31: Auto-built per incident
A32: Signal Color System | B32: Yes | C32: Semantic priority colors
... A35: Standard Onboarding | B35: Yes | C35: Remote — included
A37: VENUE ADD-ONS (capacity / guest-reporting product)
A38: Add-On | B38: Price Low / Year | C38: Price High / Year | D38: Notes
A39: AI Incident Summary | B39: $3,000 | C39: $8,000 | D39: On-demand supervisor AI brief · Cortex AI
A40: NexCort iQ Connect — Camera Integ. | B40: $6,000 | C40: $18,000 | D40: ONVIF/RTSP/WebRTC · venue camera feeds
A41: Live Caller Video Streaming | B41: $5,000 | C41: $20,000 | D41: Fan-to-security live video · WebRTC
A42: Analytics Dashboard | B42: $4,000 | C42: $10,000 | D42: Event reports · zone heat maps · scan analytics
A43: Agency Share Feature | B43: $1,500 | C43: $1,500 | D43: Per month — cross-agency incident awareness
A44: Two-Way Chat Translation (40+ langs) | B44: $2,500 | C44: $6,000 | D44: Live translation in chat
A45: SMS Location Acquisition | B45: $2,500 | C45: $6,000 | D45: Auto-reply location link on text intake
A46: Priority Support | B46: $1,000 | C46: $3,000 | D46: Per month — 4-hr response
A47: Onsite Event Support | B47: $10,000 | C47: $30,000 | D47: Per event · plus travel
A49: VENUE SECURITY DEPARTMENT / CONVENTION CENTER LICENSING
A50: Use for staff incident-reporting (security/ops departments), not capacity-based guest QR. List rates match RFP 2396IP (Javits) financial proposal — Oct 2026. Capacity tiers above remain for fan/guest reporting SKUs.
A52: A. Software licensing
A53: Item | B53: List rate | C53: Unit | D53: Notes
A54: Named user (security / ops) | B54: $2,133 | C54: per user / year | D54: iOS + Android mobile + web · unlimited incident reports within contracted dept
A55: Package example — 18 named users | B55: $38,400 | C55: per year | D55: 18 × $2,133 · RFP Addendum 1 baseline
A56: Site-wide Security Department license | B56: Same as package | C56: per year | D56: Unlimited current/future Security Dept accounts at quoted package price
A57: Additional named user | B57: $2,400 | C57: per user / year | D57: Optional · Years 4–5 escalate ≤3%
A59: B. Recurring platform components (quote separately or bundle)
A60: Component | B60: Annual list | C60: Includes | D60: Notes
A61: Web hosting and iOS / Android application distribution | B61: $6,000 | C61: AWS SaaS · iOS TestFlight/App Store · Android Google Play · 99% uptime SLA | D61: Mobile required for field security
A62: Storage, backup and 7-year retention | B62: $3,600 | C62: 500 GB included · immutable retention · daily backups | D62: Convention-center records policy
A63: Support, maintenance and updates | B63: $7,200 | C63: 8 AM–8 PM ET Mon–Fri · P1 1-hr · patches | D63: Between Standard (included) and Priority ($2,500/mo)
A64: Integration connectivity (UKG / Momentus / SSO) | B64: $2,400 | C64: Employee + event APIs + SAML keep-alive | D64: No pass-through vendor license fees
A65: Illustrative annual total (18-user package + components) | B65: $57,600 | C65: Year 1–3 fixed | D65: Optional Y4/Y5 ≤3% escalation on recurring
A67: C. Implementation — one-time (Security Department / convention)
A68: Item | B68: One-time fee | C68: Notes
A69: Project management and implementation | B69: $8,500 | C69: Kickoff · environment · PM through go-live
A70: Configuration, forms, reports and dashboards | B70: $7,500 | C70: Categories · severity · workflows · dashboards
A71: Historical migration (up to ~5,000 records / 7 years) | B71: $5,000 | C71: e.g. Resolver → NexCort iQ · attachments + audit
A72: HR / workforce API integration (e.g. UKG) | B72: $2,500 | C72: REST employee sync / lookup
A73: Event calendar API integration (e.g. Momentus) | B73: $2,500 | C73: Event population into incident location fields
A74: Single sign-on setup (SAML 2.0) | B74: $1,500 | C74: IdP config · role provisioning
A75: Testing and production go-live | B75: $2,500 | C75: UAT · regression · production cutover
A76: Training — 4 live virtual sessions (2 end-user + 2 admin) | B76: $3,000 | C76: Recordings included
A77: Illustrative implementation total | B77: $33,000 | C77: Sum of components above · fixed-fee package
A79: D. Optional unit rates (excluded from base totals)
A80: Optional item | B80: Year 1–3 rate | C80: Unit / scope
A81: Additional storage capacity | B81: $300 | C81: per 100 GB / year (min 100 GB)
A82: Additional end-user training session | B82: $1,500 | C82: up to 20 participants · 2 hrs · virtual
A83: Additional administrator training session | B83: $2,000 | C83: up to 5 admins · 3 hrs · virtual
A84: Additional customization / configuration | B84: $175 | C84: per hour
A85: Additional migration beyond quoted scope | B85: $150 | C85: per hour
A86: Weekend / extended support beyond quoted scope | B86: $500 | C86: per month · 24/7 on-call / event weekends
A87: Contract-end data export | B87: Included | C87: JSON + CSV within 15 business days
A89: SALES POSITIONING: Quote capacity tiers for guest/fan QR-NFC products. Quote Security Department licensing for convention centers / venues buying staff incident reporting (named-seat or site-wide). Do not mix models on one line without Sales Director approval. Reference: RFP 2396IP financial proposal (Apps on Demand LLC / NexCort iQ) — Oct 2026.
A90: ⚠ INTERNAL USE ONLY — Do not share without Sales Director approval.

Sheet RC Hospital
A1: NEXCORT IQ — INTERNAL PRICING GUIDE
A2: NEXCORT IQ HOSPITAL
A3: Hospitals · Health systems · EMS coordination · Pre-alert intake · MCI support · Patient tracking
A5: BASE SUBSCRIPTION — FACILITY-BASED ANNUAL PRICING
A6: Facility Tier | B6: Licensed Beds | C6: Annual Fee | D6: Monthly Equivalent | E6: Typical Facilities
A7: Tier 1 — Small Facility | B7: Under 100 beds | C7: $18,000 | D7: $1,500 | E7: Critical access hospitals · community hospitals · urgent care
A8: Tier 2 — Mid Facility | B8: 100–300 beds | C8: $30,000 | D8: $2,500 | E8: Regional hospitals · mid-size health centers
A9: Tier 3 — Large Facility | B9: 300–600 beds | C9: $48,000 | D9: $4,000 | E9: Large regional medical centers
A10: Tier 4 — Health System | B10: 600+ beds / multi | C10: $75,000+ | D10: Custom | E10: Level I trauma · health systems · academic medical centers
A12: IMPLEMENTATION — ONE-TIME
A13: Tier | B13: Implementation Fee | C13: Includes
A14: Tier 1 — Small | B14: $10,000 | C14: Console setup · staff training · EMS coordination workflow · pre-alert config
A15: Tier 2 — Mid | B15: $18,000 | C15: All above + capacity board config · MCI protocol setup
A16: Tier 3 — Large | B16: $28,000 | C16: All above + multi-unit configuration · command integration
A17: Tier 4 — System | B17: $45,000 | C17: Full health system config · multi-facility · dedicated rollout support
A19: INCLUDED IN BASE — ALL HOSPITAL PLANS
A20: Capability | B20: Included? | C20: Notes
A21: Hospital Staff Console | B21: Yes | C21: hospital_staff role — Signal color system (red vertical)
A22: Hospital Supervisor Dashboard | B22: Yes | C22: Capacity board · pre-alert queue · MCI coordination
A23: Hospital Admin Console | B23: Yes | C23: Staff management · capacity config · MCI planning
A24: Hospital Coordinator View | B24: Yes | C24: EMS liaison · outbound alerts · hospital capacity routing
A25: Pre-Alert Intake | B25: Yes | C25: Incoming EMS pre-alerts · patient status tracking
A26: Incident Timeline | B26: Yes | C26: Auto-built per incident
A27: Signal Color System | B27: Yes | C27: Red vertical band — hospital identity
A28: Role-Based Access (4 hospital roles) | B28: Yes | C28: hospital_admin · hospital_supervisor · hospital_staff · hospital_coord
A29: QR-Based Internal Reporting | B29: Yes | C29: Staff safety reporting via QR/NFC
A30: Standard Support | B30: Yes | C30: Included in base
A31: Standard Onboarding | B31: Yes | C31: Remote — included
A33: HOSPITAL ADD-ONS
A34: Add-On | B34: Price Low / Year | C34: Price High / Year | D34: Notes
A35: AI Incident Summary | B35: $3,000 | C35: $8,000 | D35: On-demand AI summary for supervisors
A36: MCI Command Module | B36: $8,000 | C36: $20,000 | D36: Mass casualty incident coordination tools
A37: EMS Data Integration | B37: $15,000 | C37: $40,000 | D37: One-time · EMS system connectivity
A38: Agency Share Feature | B38: $1,500 | C38: $1,500 | D38: Per month — cross-agency incident awareness
A39: Analytics Dashboard | B39: $4,000 | C39: $10,000 | D39: Capacity trends · pre-alert analytics
A40: Priority Support | B40: $1,000 | C40: $3,000 | D40: Per month
A41: Onsite Training | B41: $10,000 | C41: $25,000 | D41: One-time · plus travel
A43: ⚠ INTERNAL USE ONLY — Do not share without Sales Director approval.

Sheet RC Transit
A1: NEXCORT IQ — INTERNAL PRICING GUIDE
A2: NEXCORT IQ TRANSIT
A3: Transit authorities · Bus & rail · Passenger safety reporting · Vehicle/station incidents · Two-way chat · QR/NFC
A5: BASE SUBSCRIPTION — FLEET-BASED ANNUAL PRICING
A6: Transit Tier | B6: Fleet / Daily Riders | C6: Annual Fee | D6: Monthly Equivalent | E6: Typical Agencies
A7: Tier 1 — Small System | B7: Under 50 vehicles | C7: $18,000 | D7: $1,500 | E7: Small municipal transit · rural systems · shuttle networks
A8: Tier 2 — Mid System | B8: 50–200 vehicles | C8: $32,000 | D8: $2,667 | E8: Mid-size city transit · regional rail
A9: Tier 3 — Large System | B9: 200–500 vehicles | C9: $52,000 | D9: $4,333 | E9: Major city transit authorities
A10: Tier 4 — Metro System | B10: 500+ vehicles | C10: $85,000+ | D10: Custom | E10: Large metro rail/bus · statewide transit
A12: IMPLEMENTATION — ONE-TIME
A13: Tier | B13: Implementation Fee | C13: Includes
A14: Tier 1 — Small | B14: $10,000 | C14: Console setup · QR/NFC for vehicles and stations · staff training · route configuration
A15: Tier 2 — Mid | B15: $18,000 | C15: All above + multi-route config · station zone mapping
A16: Tier 3 — Large | B16: $28,000 | C16: All above + command integration · camera planning · multi-depot config
A17: Tier 4 — Metro | B17: $45,000 | C17: Full system config · multi-line · dedicated rollout · custom workflow
A19: INCLUDED IN BASE — ALL TRANSIT PLANS
A20: Capability | B20: Included? | C20: Notes
A21: Transit Security Console | B21: Yes | C21: transit_security role — Signal color system (indigo vertical)
A22: Transit Supervisor Dashboard | B22: Yes | C22: Live route map · incident overlay · escalations
A23: Transit Admin Console | B23: Yes | C23: Route/zone setup · staff management · reporting
A24: Transit Operator View | B24: Yes | C24: Read-only · vehicle status · active incidents on route
A25: QR/NFC Passenger Reporting | B25: Yes | C25: Vehicle QR codes · station NFC tags · no app required
A26: SMS Reporting Channel | B26: Yes | C26: Passenger text intake
A27: Two-Way Chat — Passenger to Security | B27: Yes | C27: Secure messaging
A28: Photo & Video Evidence Intake | B28: Yes | C28: Attached to incident record
A29: Incident Timeline | B29: Yes | C29: Auto-built per incident
A30: Signal Color System | B30: Yes | C30: Indigo vertical band — transit identity
A31: Role-Based Access (4 transit roles) | B31: Yes | C31: transit_admin · transit_supervisor · transit_security · transit_operator
... A33: Standard Onboarding | B33: Yes | C33: Remote — included
A35: TRANSIT ADD-ONS
A36: Add-On | B36: Price Low / Year | C36: Price High / Year | D36: Notes
A37: AI Incident Summary | B37: $3,000 | C37: $8,000 | D37: On-demand AI summary for supervisors
A38: NexCort iQ Connect — Camera Integ. | B38: $6,000 | C38: $18,000 | D38: ONVIF/RTSP vehicle/station camera integration
A39: Agency Share Feature | B39: $1,500 | C39: $1,500 | D39: Per month — cross-agency incident awareness
A40: Analytics Dashboard | B40: $4,000 | C40: $10,000 | D40: Route reports · incident heat maps
A41: Two-Way Chat Translation (40+ langs) | B41: $2,500 | C41: $6,000 | D41: Passenger ↔ security translation
A42: SMS Location Acquisition | B42: $2,500 | C42: $6,000 | D42: Auto-reply location link on text intake
A43: Priority Support | B43: $1,000 | C43: $3,000 | D43: Per month
A44: Onsite Training | B44: $10,000 | C44: $25,000 | D44: One-time · plus travel
A46: ⚠ INTERNAL USE ONLY — Do not share without Sales Director approval.

Sheet Verticals Overview
A1: NEXCORT IQ — INTERNAL PRICING GUIDE
A2: NEXCORT IQ — PRODUCT VERTICALS OVERVIEW
A3: RC 911 · RC Campus · RC Venue · RC Hospital · RC Transit — side-by-side comparison
A5: PRICING MODEL BY VERTICAL
A6: Vertical | B6: Pricing Model | C6: Entry Price | D6: Top of Range | E6: Minimum Contract | F6: Notes
A7: RC 911 | B7: Per seat / month | C7: $2,800/mo | D7: $50,000/mo | E7: No stated minimum | F7: Essential → Professional → Command → Enterprise
A8: RC Campus | B8: $1.40 / enrolled student / yr | C8: $15,000/yr | D8: Unlimited | E8: $15,000/yr | F8: Enrollment-based · 30% non-user adj. built in
A9: RC Venue | B9: Capacity-based annual | C9: $18,000/yr | D9: $72,000+/yr | E9: No stated minimum | F9: Tier 1–4 by max capacity
A10: RC Hospital | B10: Facility/bed-based annual | C10: $18,000/yr | D10: $75,000+/yr | E10: No stated minimum | F10: Tier 1–4 by licensed bed count
A11: RC Transit | B11: Fleet-based annual | C11: $18,000/yr | D11: $85,000+/yr | E11: No stated minimum | F11: Tier 1–4 by vehicle count
A13: SHARED CAPABILITIES ACROSS ALL VERTICALS
A14: Capability | B14: RC 911 | C14: RC Campus | D14: RC Venue | E14: RC Hospital | F14: RC Transit | G14: Notes
A15: Signal Color System | B15: ✓ | C15: ✓ | D15: ✓ | E15: ✓ | F15: ✓ | G15: 7 semantic priority colors — all consoles
A16: QR Reporting | B16: ✓ | C16: ✓ | D16: ✓ | E16: Limited | F16: ✓ | G16: 911 = add-on · Campus/Venue/Transit = included
A17: NFC Tag Support | B17: ✓ | C17: ✓ | D17: ✓ | E17: Limited | F17: ✓ | G17: Same URL as QR — all verticals
A18: SMS Reporting | B18: ✓ | C18: ✓ | D18: ✓ | E18: — | F18: ✓
A19: Two-Way Chat | B19: ✓ | C19: ✓ | D19: ✓ | E19: — | F19: ✓
A20: Photo/Video Intake | B20: ✓ | C20: ✓ | D20: ✓ | E20: — | F20: ✓
A21: Incident Timeline | B21: ✓ | C21: ✓ | D21: ✓ | E21: ✓ | F21: ✓ | G21: Auto-built on every incident
A22: AI Incident Summary | B22: Add-on | C22: Add-on | D22: Add-on | E22: Add-on | F22: Add-on | G22: All verticals — Cortex AI
A23: NexIQ Vision™ (cameras + AI) | B23: Add-on | C23: Add-on | D23: Add-on | E23: — | F23: Add-on | G23: Add-on all · Wyze live · AI transcripts
A24: Agency Share Feature | B24: Add-on | C24: Add-on | D24: — | E24: Add-on | F24: — | G24: $1,500/mo — feature, not product
A25: CAD Integration | B25: ✓ | C25: — | D25: — | E25: — | F25: — | G25: 911 only
A26: Clery Documentation | B26: — | C26: ✓ | D26: — | E26: — | F26: — | G26: Campus only
A27: Pre-Alert / MCI Module | B27: — | C27: — | D27: — | E27: ✓ | F27: — | G27: Hospital only
A28: Smart Escalation Engine | B28: ✓ | C28: ✓ | D28: ✓ | E28: ✓ | F28: ✓ | G28: Configurable per agency
A29: SMS Location Acquisition | B29: Add-on | C29: Add-on | D29: Add-on | E29: — | F29: Add-on | G29: Auto-reply GPS link on SMS intake
A30: Role-Based Dashboard Colors | B30: ✓ | C30: ✓ | D30: ✓ | E30: ✓ | F30: ✓ | G30: Distinct band color per vertical
A31: iQ Reporting | B31: Limited | C31: ✓ | D31: ✓ | E31: ✓ | F31: ✓ | G31: Supervisor/admin only — never dispatcher
A32: Incident Context Cards | B32: ✓ | C32: ✓ | D32: ✓ | E32: ✓ | F32: ✓ | G32: Included all plans
... A41: Venue Guest Services console | B41: — | C41: — | D41: ✓ | E41: — | F41: — | G41: Not a 911 dispatch system
A43: IMPLEMENTATION FEES BY VERTICAL
A44: Vertical | B44: Smallest | C44: Largest | D44: Notes
A45: RC 911 | B45: $10,000 | C45: $150,000 | D45: Essential → Command range
A46: RC Campus | B46: $8,000 | C46: $35,000 | D46: By enrollment size
A47: RC Venue | B47: $10,000 | C47: $40,000 | D47: By capacity tier
A48: RC Hospital | B48: $10,000 | C48: $45,000 | D48: By facility tier
A49: RC Transit | B49: $10,000 | C49: $45,000 | D49: By fleet tier
A51: ⚠ INTERNAL USE ONLY — Overview only. See individual vertical sheets for complete pricing.

Sheet Feature Add-Ons
A1: NEXCORT IQ — INTERNAL PRICING GUIDE
A2: FEATURE ADD-ONS
A3: QR & NFC · Agency Share · NexIQ Vision™ · Call Assist · iQ Reporting · Command Intelligence · Vault · RCS · CAD Mesh · Translate · NG911 Assist
A5: QR & NFC CODE MANAGEMENT
A6: Generates unique reporting URLs per location. QR codes print on signs. NFC tags stick to the back of the same sign. Both open the same intake form — no app download required.
A7: Plan / Vertical | B7: QR & NFC Included? | C7: Monthly Add-On | D7: Notes
A8: RC 911 — Essential | B8: Not included | C8: $500 – $1,500 | D8: Add-on — generates QR codes for field deployment
A9: RC 911 — Professional+ | B9: Included | C9: — | D9: Included in base plan
A10: RC 911 — Command+ | B10: Included | C10: — | D10: Included in base plan
A11: RC Campus — All tiers | B11: Included | C11: — | D11: Standard zones included · extended zones add-on
A12: RC Venue — All tiers | B12: Included | C12: — | D12: Section/gate zones included
A13: RC Hospital — All tiers | B13: Limited | C13: $500 – $1,500 | D13: Staff-facing only — internal reporting
A14: RC Transit — All tiers | B14: Included | C14: — | D14: Vehicle + station QR/NFC included
A16: Capability | B16: Detail
A17: URL generation | B17: Unique per location · encoded with agency, zone, vertical
A18: QR code image | B18: PNG download · 400×400px · vertical-branded colors
A19: NFC URL | B19: Copy-to-clipboard · same URL as QR · program with NFC Tools app (free)
A20: Scan tracking | B20: QR scan count and NFC tap count tracked separately per code
A21: Deactivation | B21: Soft deactivate — scans redirect to inactive page · audit trail preserved
A22: Admin access | B22: RC platform roles can create for any agency · agency roles scoped to own agency
A23: Public intake page | B23: No login · no app · works on any smartphone · vertical-skinned form
A24: Multiple sign channels | B24: Same code = QR on front + NFC on back + SMS number on sign
A27: AGENCY SHARE — FEATURE (not a separate product)
A28: Agency Share enables controlled, consent-based incident awareness between partner agencies. It is a feature of the NexCort iQ platform — not a standalone product. Agencies must establish a partnership agreement before data sharing is enabled.
A29: Item | B29: Detail | C29: Price | D29: Notes
A30: Monthly Fee | B30: Per agency, per month | C30: $1,500/mo | D30: Each agency in the partnership pays separately
A31: Access Levels | B31: Observe (read-only) · Collaborate (comment) | C31: — | D31: Set per partnership agreement
A32: Scope | B32: Configurable per incident type or All | C32: — | D32: e.g., share only CRITICAL incidents
A33: Partnership approval | B33: Both agency admins must approve | C33: — | D33: Audited — no unilateral cross-agency access
A34: Expiry | B34: Optional expiration date per partnership | C34: — | D34: Auto-revokes at expiry
A35: Availability | B35: RC 911 · RC Campus · RC Hospital | C35: — | D35: Not available for Venue or Transit
A36: Admin UI | B36: Agency Partnership tab in NC Admin | C36: — | D36: Feature toggle — locked until partnership exists
A37: Audit trail | B37: Every cross-agency read is logged | C37: — | D37: CJIS-aware · us-east-1 only
A40: NEXIQ VISION™ — CAMERA + SCENE INTELLIGENCE
A41: NexIQ Vision™ (formerly NexCort iQ Connect) links agency and citizen cameras to the live incident, with AI scene observations and vision transcripts for authorized roles. Human-in-the-loop — not autonomous enforcement.
A42: Tier / Item | B42: Monthly Fee Low | C42: Monthly Fee High | D42: Notes
A43: NexIQ Vision — Standard (up to 10 cameras) | B43: $500 | C43: $1,500 | D43: ONVIF/RTSP · link cameras to incidents · $500 list (addon-catalog)
A44: NexIQ Vision — Professional (up to 50 cameras) | B44: $1,500 | C44: $4,000 | D44: Multi-zone · KVS streaming · $1,500 list
A45: NexIQ Vision — Enterprise (unlimited cameras) | B45: $4,000 | C45: $12,000 | D45: Dedicated KVS · multi-site routing · $4,000 list
A46: Citizen Camera Share | B46: $500 | C46: $1,500 | D46: Time-limited WebRTC share · one tap from SMS link
A47: Ring Integration | B47: $500 | C47: $2,000 | D47: OAuth · residential/commercial Ring cameras (live)
A48: Nest Integration | B48: $500 | C48: $2,000 | D48: OAuth · Nest Cam feeds (live)
A49: Verkada Integration (Phase 3) | B49: $1,000 | C49: $3,000 | D49: Enterprise Verkada API
A50: Eagle Eye Integration (Phase 3) | B50: $1,000 | C50: $3,000 | D50: Eagle Eye enterprise API
A51: Camera Integration Setup | B51: $5,000 | C51: $20,000 | D51: One-time · per provider · includes RTSP bridge config
A52: Wyze Integration | B52: $500 | C52: $2,000 | D52: Citizen Wyze share · time-limited live view
A54: SMS LOCATION ACQUISITION
A55: When a student or passenger texts the emergency number, the system auto-replies with a one-tap location link. Student taps → browser requests GPS → coordinates appear in the dispatcher console within 10 seconds.
A56: Item | B56: Monthly Fee Low | C56: Monthly Fee High | D56: Notes
A57: SMS Location Acquisition | B57: $500 | C57: $2,000 | D57: Auto-reply GPS link · tracks QR vs NFC vs SMS engagement
A58: Location Analytics | B58: $500 | C58: $1,500 | D58: Location accuracy reporting · engagement funnel
A59: Setup | B59: $2,500 | C59: $5,000 | D59: One-time · per agency
A61: IQ REPORTING — SUPERVISOR / ADMIN ANALYTICS
A62: Daily agency analytics for 911, campus, venue, transit, and hospital. Supervisor and agency-admin only — never dispatcher or front-line consoles. No dedicated catalog SKU yet; Essential add-on aligned to Command Intelligence list price.
A63: Item | B63: Monthly Fee Low | C63: Monthly Fee High | D63: Notes
A64: iQ Reporting (Essential add-on) | B64: $1,500 | C64: $4,000 | D64: Included Professional+ · supervisor/admin RBAC
A65: iQ Reporting (Professional / Command) | B65: Included | C65: Included | D65: No extra fee when base plan is Pro+
A66: Nightly + hourly aggregation | B66: Included | C66: Included | D66: 7-day backfill · per-vertical daily metrics
A67: Source: live product (IQReportingPanel). Price aligned to addon-catalog comms_intel.command_intelligence $1,500/mo.
A69: COMMUNICATIONS INTELLIGENCE
A70: Distinct from Incident Command Dashboard. Context Cards are included in every plan.
A71: Item | B71: Monthly Fee Low | C71: Monthly Fee High | D71: Notes
A72: Incident Context Cards | B72: Included | C72: Included | D72: All plans · prior calls, officer-safety flags, CAD/Vault labels
A73: Command Intelligence | B73: $1,500 | C73: $4,000 | D73: Professional+ · volume, containment, translation, repeat locations
A74: NexiQ Vault | B74: $1,200 | C74: $3,500 | D74: Command+ · historical CAD/call archive · no JMS / criminal history
A75: Source: addon-catalog comms_intel.context_cards ($0), command_intelligence ($1,500), nexiq_vault ($1,200).
A77: CALL ASSIST — NON-EMERGENCY AI CALL MANAGEMENT
A78: Standalone non-emergency product. Emergency 911 is never in scope — Safety Engine transfers immediately. Users land on /app/call-assist/* — never the 911 dispatcher workspace.
A79: Item | B79: Monthly Fee Low | C79: Monthly Fee High | D79: Notes
A80: Call Assist module | B80: $4,500 | C80: $9,000 | D80: Professional+ · greeting, triage, warm transfer, supervisor monitor
A81: Call Assist CAD Push | B81: $1,500 | C81: $3,500 | D81: Command+ · human-reviewed CAD push · fail-closed with platform write-back
A82: Call Assist RMS Drafts | B82: $1,500 | C82: $3,500 | D82: Command+ · human-reviewed RMS drafts · live Records fail-closed
A83: Call Assist TTY/TDD Routing | B83: $500 | C83: $1,500 | D83: Professional+ · TTY detection + SMS fallback
A84: Call Assist External Routing | B84: $750 | C84: $2,000 | D84: Warm-transfer / overflow routing
A85: Source: addon-catalog call_assist.* list prices.
A87: RESPONSE CONTINUITY · CAD MESH · NG911 · TRANSLATE
A88: CAD write-back stays fail-closed and is NOT in pilot base. Mesh is never free. NG911 Assist has no list SKU — scope after i3/ESInet discovery.
A89: Item | B89: Monthly Fee Low | C89: Monthly Fee High | D89: Notes
A90: Response Continuity System (RCS) | B90: $3,500 | C90: $7,500 | D90: Professional+ · silent monitor, geofence arrival, audio sentinel
A91: Multi-CAD Connector / CAD-to-CAD mesh | B91: $3,500 | C91: $8,000 | D91: Command+ · never free · additional vendor $15,000 OT
A92: Map Unit Overlays (AVL) | B92: $500 | C92: $1,500 | D92: Command+ · CAD/AVL unit markers, status, ETA
A93: NexCort Translate (ops / field) | B93: $1,000 | C93: $3,000 | D93: Campus/venue/transit/clinical — complements PSAP live translation
A94: NG911 Assist (EIDO / additional data) | B94: $2,500 | C94: $7,500 | D94: No catalog SKU — quote after NG911 discovery · not a telephony replace
A95: Mutual Aid & MCI Command | B95: $5,000 | C95: $15,000 | D95: Aligns to Incident Command suite · hospital MCI routing separate
A96: Source: addon-catalog rcs.module $3,500, cad.connector $3,500, cad.unit_overlays_avl $500, cad.additional_connector $15,000 OT. NG911 range is internal guidance only.
A98: VERTICAL OPERATIONS & PLATFORM SECURITY
A99: Clery is campus-only and is not legal advice. Physical lock/unlock commands are a separate fail-closed flag.
A100: Item | B100: Monthly Fee Low | C100: Monthly Fee High | D100: Notes
A101: Emergency Alert Broadcast | B101: $1,500 | C101: $4,000 | D101: Professional+ · campus/venue/transit occupant notification
A102: Emergency Alert Short Code (pass-through) | B102: $750 | C102: $2,000 | D102: Command+ · 8–12 week procurement · not sub-3s SMS
A103: Clery Act Compliance Module | B103: $417 | C103: $1,250 | D103: Campus Command+ · CSA registry, Daily Crime Log, ASR stats
A104: Physical Security Ingest | B104: $2,500 | C104: $6,000 | D104: Command+ · fire panel / access-control events · no auto unlock
A105: Hospital Routing Module | B105: $4,000 | C105: $8,000 | D105: Hospital Professional+ · divert, ED routing, trauma bay
A106: Network Access Controls | B106: $500 | C106: $1,500 | D106: Professional+ · IP allowlists + time-window gates
A107: Deception Shield | B107: $2,000 | C107: $5,000 | D107: Command+ · honeypot / decoy paths for unauthorized-access detection
A108: Extended Audit Retention | B108: $1,000 | C108: $3,000 | D108: Command+ · beyond plan retention floor
A109: API Keys & Webhooks | B109: $500 | C109: $1,500 | D109: Professional+ · scoped outbound credentials
A110: Grant Success Package | B110: $2,500 | C110: $2,500 | D110: One-time · Professional+ · grant-ready exports (not monthly)
A111: Source: addon-catalog vertical.alerts, campus.clery, physical.security, hospital.routing, platform_security.*, grant_success_package $2,500 OT.
A113: ⚠ INTERNAL USE ONLY — Feature add-on pricing. Agency Share is a FEATURE, not a product. NexIQ Vision™ / Call Assist / Vault / mesh are never free. CAD write-back is fail-closed. Do not quote NexiQ sales intelligence to agencies.

Sheet AI Intelligence
A1: NEXCORT IQ — INTERNAL PRICING GUIDE
A2: AI & CALL INTELLIGENCE ADD-ONS
A3: Triage workflows · Confidence scoring · Model redundancy · Summarization · Custom tuning
A5: AI TRIAGE WORKFLOWS
A6: Tier | B6: Rules / Coverage | C6: Monthly Fee | D6: Notes
A7: Basic | B7: 5–10 custom rules | C7: 2500 | D7: Single emergency type
A8: Standard | B8: 10–25 rules, 3–5 types | C8: 5000 | D8: Most agencies — recommended
A9: Premium | B9: 25+ rules, all types | C9: 7500 | D9: Full coverage
A11: AI MODEL REDUNDANCY
A12: Level | B12: Monthly Fee Low | C12: Monthly Fee High | D12: Notes
A13: Secondary AI Model Review | B13: 2000 | C13: 6000 | D13: By volume
A14: Tertiary AI Model Fallback | B14: 2000 | C14: 6000 | D14: Adds resilience — recommended for Command+
A16: AI CONFIDENCE & SCORING
A17: Tier | B17: Monthly Fee | C17: Notes
A18: Basic Confidence Scoring | B18: 1500
A19: Advanced Confidence Scoring | B19: 3500
A20: Premium Multi-Factor Scoring | B20: 5000 | C20: Recommended for Command+
A21: AI QA Scoring Model | B21: 2500
A23: AI INCIDENT SUMMARIZATION
A24: Volume Tier | B24: Monthly Fee | C24: Notes
A25: Basic (<5K calls/month) | B25: 1500
A26: Standard (5K–20K calls/month) | B26: 3500
A27: Premium (20K+ calls/month) | B27: 5000
A29: AI CUSTOM DEVELOPMENT & TUNING
A30: Item | B30: Price Low | C30: Price High | D30: Type | E30: Notes
A31: AI Dispatcher Recommendation Engine | B31: 2500 | C31: 10000 | D31: / month
A32: Custom Agency AI Prompts / Playbooks | B32: 10000 | C32: 50000 | D32: One-time
A33: Custom Emergency-Type Workflow Tuning | B33: 5000 | C33: 25000 | D33: Per workflow
A34: AI Post-Incident Review Package | B34: 2500 | C34: 10000 | D34: / month
A36: SALES POSITIONING — AI Add-Ons
A37: Position AI as decision support, not a replacement for dispatcher judgment.
A38: Reduces cognitive load and improves consistency during high-pressure calls.
A39: Custom prompts/playbooks are high-value, high-margin — scope carefully.
A40: ⚠ INTERNAL USE ONLY

Sheet Client Quote
D1: NEXCORT IQ
A5: Apps on Demand LLC d/b/a NexCort iQ | Intelligence at the Speed of Response
A7: ='Quote Builder'!D8&" — Service Proposal"
A8: ='Quote Builder'!D9
A10: QUOTE DETAILS
A11: Plan Selected | F11: ='Quote Builder'!D15
A12: Contract Term | F12: ='Quote Builder'!D16
A13: Dispatcher Seats | F13: ='Quote Builder'!D10
A14: Admin / Supervisor Seats | F14: ='Quote Builder'!D11
A15: Est. Call Volume / Month | F15: ='Quote Builder'!D12&" calls"
A16: Quote Prepared | F16: =TODAY()
A18: PRICING BREAKDOWN
A19: # | B19: Description | F19: Monthly ($) | H19: One-Time / Annual ($)
A20: 1 | B20: ="Base Plan — "&'Quote Builder'!D15&" ("&'Quote Builder'!D10&" dispatcher seats)" | F20: ='Quote Builder'!J15 | H20: ='Quote Builder'!J15*12
A21: 2 | B21: Dispatcher Seat Overage | F21: =IF('Quote Builder'!J17>0,'Quote Builder'!J17,"—") | H21: =IF('Quote Builder'!J17>0,'Quote Builder'!J17*12,"—")
A22: 3 | B22: Admin / Supervisor Seat Overage | F22: =IF('Quote Builder'!J18>0,'Quote Builder'!J18,"—") | H22: =IF('Quote Builder'!J18>0,'Quote Builder'!J18*12,"—")
A23: 4 | B23: Setup & Implementation Fee | F23: — | H23: ='Quote Builder'!J19
A24: ADD-ON MODULES
A25: 5 | B25: CAD Integration | F25: =IF('Quote Builder'!J25>0,'Quote Builder'!J25,"—") | H25: =IF('Quote Builder'!J25>0,'Quote Builder'!J25*12,"—")
A26: 6 | B26: AI Triage Workflows | F26: =IF('Quote Builder'!J26>0,'Quote Builder'!J26,"—") | H26: =IF('Quote Builder'!J26>0,'Quote Builder'!J26*12,"—")
A27: 7 | B27: AI Confidence Scoring | F27: =IF('Quote Builder'!J27>0,'Quote Builder'!J27,"—") | H27: =IF('Quote Builder'!J27>0,'Quote Builder'!J27*12,"—")
A28: 8 | B28: AI Incident Summarization | F28: =IF('Quote Builder'!J28>0,'Quote Builder'!J28,"—") | H28: =IF('Quote Builder'!J28>0,'Quote Builder'!J28*12,"—")
A29: 9 | B29: AI Dispatcher Recommendation Engine | F29: =IF('Quote Builder'!J29>0,'Quote Builder'!J29,"—") | H29: =IF('Quote Builder'!J29>0,'Quote Builder'!J29*12,"—")
A30: 10 | B30: Enhanced Transcription Accuracy | F30: =IF('Quote Builder'!J30>0,'Quote Builder'!J30,"—") | H30: =IF('Quote Builder'!J30>0,'Quote Builder'!J30*12,"—")
A31: 11 | B31: Speaker Diarization | F31: =IF('Quote Builder'!J31>0,'Quote Builder'!J31,"—") | H31: =IF('Quote Builder'!J31>0,'Quote Builder'!J31*12,"—")
A32: 12 | B32: Live Translation | F32: =IF('Quote Builder'!J32>0,'Quote Builder'!J32,"—") | H32: =IF('Quote Builder'!J32>0,'Quote Builder'!J32*12,"—")
A33: 13 | B33: Language Packs | F33: =IF('Quote Builder'!J33>0,'Quote Builder'!J33,"—") | H33: =IF('Quote Builder'!J33>0,'Quote Builder'!J33*12,"—")
A34: 14 | B34: Caller SMS Link Generation | F34: =IF('Quote Builder'!J34>0,'Quote Builder'!J34,"—") | H34: =IF('Quote Builder'!J34>0,'Quote Builder'!J34*12,"—")
A35: 15 | B35: Caller Photo Upload | F35: =IF('Quote Builder'!J35>0,'Quote Builder'!J35,"—") | H35: =IF('Quote Builder'!J35>0,'Quote Builder'!J35*12,"—")
A36: 16 | B36: Caller Video Upload | F36: =IF('Quote Builder'!J36>0,'Quote Builder'!J36,"—") | H36: =IF('Quote Builder'!J36>0,'Quote Builder'!J36*12,"—")
... A43: 23 | B43: Support Package Upgrade | F43: =IF('Quote Builder'!J43>0,'Quote Builder'!J43,"—") | H43: =IF('Quote Builder'!J43>0,'Quote Builder'!J43*12,"—")
A44: 24 | B44: Onsite Services | F44: — | H44: =IF('Quote Builder'!J44>0,'Quote Builder'!J44,"—")
A45: 25 | B45: Training Package | F45: — | H45: =IF('Quote Builder'!J45>0,'Quote Builder'!J45,"—")
A46: 26 | B46: Call Assist (non-emergency) | F46: =IF('Quote Builder'!J46>0,'Quote Builder'!J46,"—") | H46: =IF('Quote Builder'!J46>0,'Quote Builder'!J46*12,"—")
A47: 27 | B47: NexIQ Vision™ | F47: =IF('Quote Builder'!J47>0,'Quote Builder'!J47,"—") | H47: =IF('Quote Builder'!J47>0,'Quote Builder'!J47*12,"—")
A48: 28 | B48: iQ Reporting | F48: =IF('Quote Builder'!J48>0,'Quote Builder'!J48,"—") | H48: =IF('Quote Builder'!J48>0,'Quote Builder'!J48*12,"—")
A49: 29 | B49: Command Intelligence | F49: =IF('Quote Builder'!J49>0,'Quote Builder'!J49,"—") | H49: =IF('Quote Builder'!J49>0,'Quote Builder'!J49*12,"—")
A50: 30 | B50: NexiQ Vault | F50: =IF('Quote Builder'!J50>0,'Quote Builder'!J50,"—") | H50: =IF('Quote Builder'!J50>0,'Quote Builder'!J50*12,"—")
A51: 31 | B51: Response Continuity (RCS) | F51: =IF('Quote Builder'!J51>0,'Quote Builder'!J51,"—") | H51: =IF('Quote Builder'!J51>0,'Quote Builder'!J51*12,"—")
A52: 32 | B52: CAD-to-CAD mesh / Multi-CAD | F52: =IF('Quote Builder'!J52>0,'Quote Builder'!J52,"—") | H52: =IF('Quote Builder'!J52>0,'Quote Builder'!J52*12,"—")
A53: 33 | B53: Emergency Alert Broadcast | F53: =IF('Quote Builder'!J53>0,'Quote Builder'!J53,"—") | H53: =IF('Quote Builder'!J53>0,'Quote Builder'!J53*12,"—")
A54: 34 | B54: NexCort Translate (ops / field) | F54: =IF('Quote Builder'!J54>0,'Quote Builder'!J54,"—") | H54: =IF('Quote Builder'!J54>0,'Quote Builder'!J54*12,"—")
A55: 35 | B55: NG911 Assist | F55: =IF('Quote Builder'!J55>0,'Quote Builder'!J55,"—") | H55: =IF('Quote Builder'!J55>0,'Quote Builder'!J55*12,"—")
B57: Subtotal — Monthly Recurring | F57: ='Quote Builder'!J15+'Quote Builder'!J17+'Quote Builder'!J18+SUMPRODUCT(('Quote Builder'!J26:J43)*1)+SUMPRODUCT(('Quote Builder'!J46:J55)*1) | H57: =('Quote Builder'!J15+'Quote Builder'!J17+'Quote Builder'!J18+SUMPRODUCT(('Quote Builder'!J26:J43)*1)+SUMPRODUCT(('Quote Builder'!J46:J55)*1))*12
B58: Subtotal — One-Time Fees | F58: — | H58: ='Quote Builder'!J19+'Quote Builder'!J25+'Quote Builder'!J44+'Quote Builder'!J45
B59: =IF(MAX('Quote Builder'!F16,'Quote Builder'!D22)>0,"Discount ("&TEXT(MAX('Quote Builder'!F16,'Quote Builder'!D22),"0%")&") Applied","No Discount") | F59: =IFERROR(-F57*MAX('Quote Builder'!F16,'Quote Builder'!D22),0) | H59: =IFERROR(-H58*MAX('Quote Builder'!F16,'Quote Builder'!D22),0)
B61: ★ TOTAL MONTHLY | F61: =F57+F59 | H61: =(F57+F59)*12
B62: ★ TOTAL ONE-TIME FEES | F62: — | H62: =H58+H59
B63: ★ ESTIMATED ANNUAL INVESTMENT | F63: — | H63: =(F57+F59)*12+(H58+H59)
A65: TERMS & NEXT STEPS
A66: • This proposal is valid for 30 days from the date of issue.
A67: • Pricing is based on the selections above. Final contract subject to signed MSA and SOW.
A68: • CAD integration scoped separately after discovery. Write-back not included in pilot base.
A69: • Travel for onsite services billed separately at federal GSA rates.
A70: • All fees are in USD. Government tax exemption honored upon receipt of certificate.
A71: • To proceed: return signed Pilot Scope Agreement or contact your NexCort iQ representative.
A73: NexCort iQ | Apps on Demand LLC | intelligence@rapidcortex.us | rapidcortex.us | CONFIDENTIAL — NOT FOR DISTRIBUTION

Sheet Quote Builder
A1: NEXCORT IQ
A2: INTERACTIVE QUOTE BUILDER — INTERNAL USE ONLY
A3: 🟡 Yellow = you answer | 🔵 Blue = auto-calculated | See "Client Quote" tab for printable output
B5: Question / Line Item | C5: Category | D5: Your Answer (dropdown) | F5: Std Unit Price | H5: Override Price | J5: Monthly Total
A6: Override Price = leave blank to use standard. Enter a custom value to override for this quote only. Red border = override active.
A7: SECTION 1 — AGENCY PROFILE
A8: 1 | B8: Agency / Department Name
A9: 2 | B9: Contact Name & Title
A10: 3 | B10: Number of Dispatcher Seats
A11: 4 | B11: Number of Admin / Supervisor Seats
A12: 5 | B12: Estimated Call Volume / Month
A14: SECTION 2 — BASE PLAN SELECTION
A15: 6 | B15: Base Plan | F15: =IF(D15="Essential",IF(D10<=3,2800,IF(D10<=6,4200,IF(D10<=8,5400,IF(D10<=10,6000,6000)))),IF(D15="Professional",IF(D10<=10,8500,IF(D10<=18,13000,IF(D10<=23,15500,IF(D10<=25,18000,18000)))),IF(D15="Command",IF(D10<=25,22500,IF(D10<=50,31000,IF(D10<=65,40000,IF(D10<=75,50000,50000)))),IF(D15="Enterprise",80000,0)))) | J15: =IF(ISNUMBER(H15),H15,F15)
A16: 7 | B16: Contract Term | F16: =IF(D16="1-year",0,IF(D16="2-year",0.15,IF(D16="3-year",0.2,0))) | J16: Discount rate — applied in summary
A17: 8 | B17: Dispatcher Seat Overage (auto) | F17: =IF(D15="Essential",150,IF(D15="Professional",125,IF(D15="Command",100,IF(D15="Enterprise",88,0)))) | J17: =IF(ISNUMBER(H17),H17,MAX(0,D10-IF(D15="Essential",10,IF(D15="Professional",25,IF(D15="Command",75,IF(D15="Enterprise",200,0)))))*F17)
A18: 9 | B18: Admin / Supervisor Seat Overage (auto) | F18: =IF(D15="Essential",100,IF(D15="Professional",100,IF(D15="Command",85,IF(D15="Enterprise",90,0)))) | J18: =IF(ISNUMBER(H18),H18,MAX(0,D11-IF(D15="Essential",3,IF(D15="Professional",8,IF(D15="Command",20,IF(D15="Enterprise",30,0)))))*F18)
A19: 10 | B19: Setup & Implementation Fee | F19: =IF(D15="Essential",IF(D10<=3,10000,IF(D10<=6,12500,IF(D10<=8,17500,22500))),IF(D15="Professional",IF(D10<=10,25000,IF(D10<=18,35000,IF(D10<=23,45000,55000))),IF(D15="Command",IF(D10<=25,75000,IF(D10<=50,90000,IF(D10<=65,110000,130000))),IF(D15="Enterprise",200000,0)))) | J19: =IF(ISNUMBER(H19),H19,F19)
A21: =IF(MAX(F16,D22)>0.15,"⚠ DISCOUNT >15% — Sales Director approval required","✓ Discount within standard range")
A22: 11 | B22: Additional Discount Override (0–25%) | F22: =F16 | J22: =MAX(F16,D22)
A24: SECTION 3 — ADD-ON MODULES (all add-ons shown — select None to exclude)
A25: 12 | B25: CAD Integration | F25: =IF(D25="None",0,IF(D25="Discovery Workshop ($7,500)",7500,IF(D25="Discovery Workshop Advanced ($15,000)",15000,IF(D25="Vendor Coordination Basic ($10,000)",10000,IF(D25="Vendor Coordination Premium ($25,000)",25000,IF(D25="Read-Only Tier 1 ($35,000)",35000,IF(D25="Read-Only Tier 2 ($55,000)",55000,IF(D25="Read-Only Tier 3 ($75,000)",75000,IF(D25="Read-Only Tier 4 ($100,000)",100000,IF(D25="Assisted Write-Back T1 ($75,000)",75000,IF(D25="Assisted Write-Back T2 ($125,000)",125000,IF(D25="Assisted Write-Back T3 ($175,000)",175000,IF(D25="Automated Write-Back T1 ($150,000)",150000,IF(D25="Automated Write-Back T2 ($250,000)",250000,0)))))))))))))) | J25: =IF(ISNUMBER(H25),H25,F25)
A26: 13 | B26: AI Triage Workflows | F26: =IF(D26="None",0,IF(D26="Basic 5-10 rules ($2,500/mo)",2500,IF(D26="Standard 10-25 rules ($5,000/mo)",5000,IF(D26="Premium 25+ rules ($7,500/mo)",7500,0)))) | J26: =IF(ISNUMBER(H26),H26,F26)
A27: 14 | B27: AI Confidence Scoring | F27: =IF(D27="None",0,IF(D27="Basic ($1,500/mo)",1500,IF(D27="Advanced ($3,500/mo)",3500,IF(D27="Premium ($5,000/mo)",5000,0)))) | J27: =IF(ISNUMBER(H27),H27,F27)
A28: 15 | B28: AI Incident Summarization | F28: =IF(D28="None",0,IF(D28="Basic <5K calls ($1,500/mo)",1500,IF(D28="Standard 5K-20K calls ($3,500/mo)",3500,IF(D28="Premium 20K+ calls ($5,000/mo)",5000,0)))) | J28: =IF(ISNUMBER(H28),H28,F28)
A29: 16 | B29: AI Dispatcher Recommendation Engine | F29: =IF(D29="None",0,IF(D29="Standard ($2,500/mo)",2500,IF(D29="Advanced ($10,000/mo)",10000,0))) | J29: =IF(ISNUMBER(H29),H29,F29)
A30: 17 | B30: Enhanced Transcription Accuracy | F30: =IF(D30="None",0,IF(D30="Tier 1 <5K calls ($1,500/mo)",1500,IF(D30="Tier 2 5K-15K calls ($3,000/mo)",3000,IF(D30="Tier 3 15K+ calls ($5,000/mo)",5000,0)))) | J30: =IF(ISNUMBER(H30),H30,F30)
A31: 18 | B31: Speaker Diarization | F31: =IF(D31="None",0,IF(D31="Tier 1 <5K ($1,000/mo)",1000,IF(D31="Tier 2 5K-15K ($2,500/mo)",2500,IF(D31="Tier 3 15K+ ($4,000/mo)",4000,0)))) | J31: =IF(ISNUMBER(H31),H31,F31)
A32: 19 | B32: Live Translation | F32: =IF(OR(D32="None (included Pro+)",D32="None"),0,IF(D32="Tier 1 2-3 languages ($2,500/mo)",2500,IF(D32="Tier 2 4-6 languages ($5,500/mo)",5500,IF(D32="Tier 3 7-10 languages ($8,000/mo)",8000,IF(D32="Tier 4 10+ languages ($10,000/mo)",10000,0))))) | J32: =IF(D15="Essential",IF(ISNUMBER(H32),H32,F32),0)
A33: 20 | B33: Language Packs (Top 10 Languages) | F33: =IF(D33="None",0,IF(D33="Top 10 Languages ($3,500/mo)",3500,IF(D33="Top 15 Languages ($5,000/mo)",5000,0))) | J33: =IF(ISNUMBER(H33),H33,F33)
A34: 21 | B34: Caller SMS Link Generation | F34: =IF(D34="None",0,IF(D34="Basic <500 links ($1,500/mo)",1500,IF(D34="Standard ($5,000/mo)",5000,0))) | J34: =IF(ISNUMBER(H34),H34,F34)
A35: 22 | B35: Caller Photo Upload | F35: =IF(D35="None",0,IF(D35="Basic 500 photos ($1,000/mo)",1000,IF(D35="Standard 2K photos ($2,500/mo)",2500,IF(D35="Premium 5K+ photos ($4,000/mo)",4000,0)))) | J35: =IF(ISNUMBER(H35),H35,F35)
A36: 23 | B36: Caller Video Upload | F36: =IF(D36="None",0,IF(D36="Standard ($2,500/mo)",2500,IF(D36="Premium ($8,500/mo)",8500,0))) | J36: =IF(ISNUMBER(H36),H36,F36)
A37: 24 | B37: Live Caller Video Streaming | F37: =IF(D37="None",0,IF(D37="Standard ($5,000/mo)",5000,IF(D37="Premium ($20,000/mo)",20000,0))) | J37: =IF(ISNUMBER(H37),H37,F37)
A38: 25 | B38: Media Audit Trail & Redaction | F38: =IF(D38="None",0,IF(D38="Audit Trail ($1,500/mo)",1500,IF(D38="Audit + Redaction ($7,500/mo)",7500,0))) | J38: =IF(ISNUMBER(H38),H38,F38)
A39: 26 | B39: QA Review Tools | F39: =IF(OR(D39="None (included Pro+)",D39="None"),0,IF(D39="Basic Scorecards ($1,000/mo)",1000,IF(D39="Full QA Suite ($3,500/mo)",3500,IF(D39="QA Suite + AI Grading ($6,000/mo)",6000,0)))) | J39: =IF(D15="Essential",IF(ISNUMBER(H39),H39,F39),0)
A40: 27 | B40: Team Performance Dashboards | F40: =IF(OR(D40="None (included Pro+)",D40="None"),0,IF(D40="Standard ($2,000/mo)",2000,IF(D40="Advanced ($7,500/mo)",7500,0))) | J40: =IF(D15="Essential",IF(ISNUMBER(H40),H40,F40),0)
A41: 28 | B41: Incident Command Suite | F41: =IF(OR(D41="None (included Command+)",D41="None"),0,IF(D41="Basic Package ($5,000/mo)",5000,IF(D41="Full Command Suite ($12,500/mo)",12500,0))) | J41: =IF(OR(D15="Essential",D15="Professional"),IF(ISNUMBER(H41),H41,F41),0)
A42: 29 | B42: Reliability & Tech Ops | F42: =IF(OR(D42="None (included Command+)",D42="None"),0,IF(D42="Basic Monitoring ($2,500/mo)",2500,IF(D42="Full Reliability Suite ($7,500/mo)",7500,0))) | J42: =IF(OR(D15="Essential",D15="Professional"),IF(ISNUMBER(H42),H42,F42),0)
A43: 30 | B43: Support Package | F43: =IF(OR(D43="Standard (Included)",D43=""),0,IF(D43="Priority Small <25 users ($2,500/mo)",2500,IF(D43="Priority Medium 25-75 ($5,000/mo)",5000,IF(D43="Priority Large 75+ ($7,500/mo)",7500,0)))) | J43: =IF(D15="Essential",IF(ISNUMBER(H43),H43,F43),0)
A44: 31 | B44: Onsite Services | F44: =IF(D44="None",0,IF(D44="Discovery Visit ($10,000)",10000,IF(D44="Pilot Launch Support ($35,000)",35000,IF(D44="Go-Live Support ($65,000)",65000,IF(D44="Full Program ($100,000)",100000,0))))) | J44: =IF(ISNUMBER(H44),H44,F44)
A45: 32 | B45: Training Package | F45: =IF(OR(D45="Standard Onboarding (Included)",D45=""),0,IF(D45="Remote Package ($5,000)",5000,IF(D45="Onsite Dispatcher ($20,000)",20000,IF(D45="Onsite Supervisor ($20,000)",20000,IF(D45="Train-the-Trainer ($30,000)",30000,IF(D45="Custom Program ($50,000)",50000,0)))))) | J45: =IF(ISNUMBER(H45),H45,F45)
A46: 33 | B46: Call Assist (non-emergency) | D46: None | F46: =IF(D46="None",0,IF(D46="Module ($4,500/mo)",4500,IF(D46="Module + CAD Push ($6,000/mo)",6000,IF(D46="Full (module+CAD+RMS) ($7,500/mo)",7500,0)))) | J46: =IF(ISNUMBER(H46),H46,F46)
A47: 34 | B47: NexIQ Vision™ | D47: None | F47: =IF(D47="None",0,IF(D47="Standard 10 cameras ($500/mo)",500,IF(D47="Professional 50 cameras ($1,500/mo)",1500,IF(D47="Enterprise unlimited ($4,000/mo)",4000,0)))) | J47: =IF(ISNUMBER(H47),H47,F47)
A48: 35 | B48: iQ Reporting | D48: None | F48: =IF(OR(D48="None (included Pro+)",D48="None"),0,IF(D48="Essential add-on ($1,500/mo)",1500,IF(D48="Essential add-on ($3,500/mo)",3500,0))) | J48: =IF(D15="Essential",IF(ISNUMBER(H48),H48,F48),0)
A49: 36 | B49: Command Intelligence | D49: None | F49: =IF(D49="None",0,IF(D49="Standard ($1,500/mo)",1500,IF(D49="Advanced ($4,000/mo)",4000,0))) | J49: =IF(ISNUMBER(H49),H49,F49)
A50: 37 | B50: NexiQ Vault | D50: None | F50: =IF(D50="None",0,IF(D50="Standard ($1,200/mo)",1200,IF(D50="Extended ($3,500/mo)",3500,0))) | J50: =IF(ISNUMBER(H50),H50,F50)
A51: 38 | B51: Response Continuity (RCS) | D51: None | F51: =IF(D51="None",0,IF(D51="Module ($3,500/mo)",3500,IF(D51="Module + sentinel ($7,500/mo)",7500,0))) | J51: =IF(ISNUMBER(H51),H51,F51)
A52: 39 | B52: CAD-to-CAD mesh / Multi-CAD | D52: None | F52: =IF(D52="None",0,IF(D52="Multi-CAD Connector ($3,500/mo)",3500,IF(D52="Regional mesh ($8,000/mo)",8000,0))) | J52: =IF(ISNUMBER(H52),H52,F52)
A53: 40 | B53: Emergency Alert Broadcast | D53: None | F53: =IF(D53="None",0,IF(D53="Alerts ($1,500/mo)",1500,IF(D53="Alerts + short code ($2,250/mo)",2250,0))) | J53: =IF(ISNUMBER(H53),H53,F53)
A54: 41 | B54: NexCort Translate (ops / field) | D54: None | F54: =IF(D54="None",0,IF(D54="Ops Translate ($1,000/mo)",1000,IF(D54="Ops Translate ($3,000/mo)",3000,0))) | J54: =IF(ISNUMBER(H54),H54,F54)
A55: 42 | B55: NG911 Assist | D55: None | F55: =IF(D55="None",0,IF(D55="Discovery-scoped ($2,500/mo)",2500,IF(D55="Discovery-scoped ($7,500/mo)",7500,0))) | J55: =IF(ISNUMBER(H55),H55,F55)
A57: SECTION 4 — QUOTE SUMMARY (auto-calculated)
A58: Monthly Recurring (before discount) | D58: Monthly | J58: =IFERROR(J15+J17+J18+SUM(J26:J43)+SUM(J46:J55),0)
A59: One-Time Fees (setup + CAD + onsite + training) | D59: One-Time | J59: =IFERROR(J19+J25+J44+J45,0)
A60: =IF(MAX(F16,D22)>0,"Discount ("&TEXT(MAX(F16,D22),"0%")&") applied","No discount")
A61: Monthly Discount Amount | D61: Deduction | J61: =IFERROR(-J58*MAX(F16,D22),0)
A62: One-Time Discount Amount | D62: Deduction | J62: =IFERROR(-J59*MAX(F16,D22),0)
A64: ★ TOTAL MONTHLY (after discount) | D64: TOTAL | J64: =IFERROR(J58+J61,0)
A65: ★ TOTAL ONE-TIME (after discount) | D65: TOTAL | J65: =IFERROR(J59+J62,0)
A66: ★ ESTIMATED ANNUAL TOTAL (Monthly×12 + One-Time) | D66: TOTAL | J66: =IFERROR(J64*12+J65,0)
A67: Per Seat / Month | J67: =IFERROR(J64/(D10+D11),"")
A69: ⚠ INTERNAL USE ONLY — See "Client Quote" tab for printable version. All quotes require Sales Director review before sending.
A200: REFS | B200: 54 | C200: 55
