Workbook

Sheet Assumptions
A1: NexCort iQ — 3-Year Projection Model: Assumptions
A4: CORE — ACV by plan (real, from internal pricing schedule)
A5: Plan | B5: Low ($) | C5: High ($) | D5: Midpoint ACV ($) — used in model
A6: Essential | B6: 33600 | C6: 72000 | D6: =AVERAGE(B6:C6) -> 52800
A7: Professional | B7: 102000 | C7: 216000 | D7: =AVERAGE(B7:C7) -> 159000
A8: Command | B8: 270000 | C8: 600000 | D8: =AVERAGE(B8:C8) -> 435000
A9: Enterprise / Statewide | B9: 720000 | C9: 10000000 | D9: =AVERAGE(B9:C9) -> 5360000
A11: CAMPUS & VENUE — pricing (real model; venue ACV requires your input)
A12: Campus rate per enrolled student / year | B12: 1.4
A13: Venue — blended ACV per venue customer (ENTER ASSUMPTION — no public per-tier $ on file) | B13: 12350
A15: CUSTOMER GROWTH — ENTER ASSUMPTION (new customers added during each year)
A16: Segment | B16: Year 1 new | C16: Year 2 new | D16: Year 3 new | E16: Annual churn % (of prior base)
A17: Core — Essential | B17: 1 | C17: 2 | D17: 8 | E17: 0
A18: Core — Professional | B18: 1 | C18: 5 | D18: 6 | E18: 0
A19: Core — Command | B19: 0 | C19: 1 | D19: 5 | E19: 0
A20: Core — Enterprise / Statewide | B20: 0 | C20: 0 | D20: 2 | E20: 0
A21: Campus (customers; pair with enrollment below) | B21: 2 | C21: 12 | D21: 28 | E21: 0
A22: Venue | B22: 2 | C22: 6 | D22: 18 | E22: 0
A24: Average enrolled students per Campus customer (ENTER ASSUMPTION) | B24: 8524
A26: COST ASSUMPTIONS — ENTER ASSUMPTION (% of that year's total revenue, unless noted)
A27: Cost of service / hosting (COGS) % | B27: 0
A28: Sales & marketing % | B28: 0
A29: R&D / engineering % | B29: 0
A30: General & administrative — fixed $/year | B30: 0

Sheet 3-Year Projection
A1: NexCort iQ — 3-Year Revenue & Cost Projection
A2: 100% formula-driven from the Assumptions tab. No revenue, customer, or cost figures are hardcoded here — change Assumptions and this entire sheet recalculates.
B4: Year 1 | C4: Year 2 | D4: Year 3
A5: Ending customers — by segment
A6: Core — Essential | B6: =Assumptions!B17 -> 1 | C6: =B6*(1-Assumptions!E17)+Assumptions!C17 -> 3 | D6: =C6*(1-Assumptions!E17)+Assumptions!D17 -> 11
A7: Core — Professional | B7: =Assumptions!B18 -> 1 | C7: =B7*(1-Assumptions!E18)+Assumptions!C18 -> 6 | D7: =C7*(1-Assumptions!E18)+Assumptions!D18 -> 12
A8: Core — Command | B8: =Assumptions!B19 -> 0 | C8: =B8*(1-Assumptions!E19)+Assumptions!C19 -> 1 | D8: =C8*(1-Assumptions!E19)+Assumptions!D19 -> 6
A9: Core — Enterprise / Statewide | B9: =Assumptions!B20 -> 0 | C9: =B9*(1-Assumptions!E20)+Assumptions!C20 -> 0 | D9: =C9*(1-Assumptions!E20)+Assumptions!D20 -> 2
A10: Campus (customers; pair with enrollment below) | B10: =Assumptions!B21 -> 2 | C10: =B10*(1-Assumptions!E21)+Assumptions!C21 -> 14 | D10: =C10*(1-Assumptions!E21)+Assumptions!D21 -> 42
A11: Venue | B11: =Assumptions!B22 -> 2 | C11: =B11*(1-Assumptions!E22)+Assumptions!C22 -> 8 | D11: =C11*(1-Assumptions!E22)+Assumptions!D22 -> 26
A13: Revenue by segment ($)
A14: Core — Essential | B14: =B6*Assumptions!$D$6 -> 52800 | C14: =C6*Assumptions!$D$6 -> 158400 | D14: =D6*Assumptions!$D$6 -> 580800
A15: Core — Professional | B15: =B7*Assumptions!$D$7 -> 159000 | C15: =C7*Assumptions!$D$7 -> 954000 | D15: =D7*Assumptions!$D$7 -> 1908000
A16: Core — Command | B16: =B8*Assumptions!$D$8 -> 0 | C16: =C8*Assumptions!$D$8 -> 435000 | D16: =D8*Assumptions!$D$8 -> 2610000
A17: Core — Enterprise / Statewide | B17: =B9*Assumptions!$D$9 -> 0 | C17: =C9*Assumptions!$D$9 -> 0 | D17: =D9*Assumptions!$D$9 -> 10720000
A18: Campus (customers; pair with enrollment below) | B18: =B10*Assumptions!$B$24*Assumptions!$B$12 -> 23867.2 | C18: =C10*Assumptions!$B$24*Assumptions!$B$12 -> 167070.4 | D18: =D10*Assumptions!$B$24*Assumptions!$B$12 -> 501211.2
A19: Venue | B19: =B11*Assumptions!$B$13 -> 24700 | C19: =C11*Assumptions!$B$13 -> 98800 | D19: =D11*Assumptions!$B$13 -> 321100
A21: Total Revenue | B21: =SUM(B14:B19) -> 260367.2 | C21: =SUM(C14:C19) -> 1813270.4 | D21: =SUM(D14:D19) -> 16641111
A23: Cost of service / hosting (COGS) | B23: =B21*Assumptions!$B$27 -> 0 | C23: =C21*Assumptions!$B$27 -> 0 | D23: =D21*Assumptions!$B$27 -> 0
A24: Gross Profit | B24: =B21-B23 -> 260367.2 | C24: =C21-C23 -> 1813270.4 | D24: =D21-D23 -> 16641111
A26: Sales & marketing | B26: =B21*Assumptions!$B$28 -> 0 | C26: =C21*Assumptions!$B$28 -> 0 | D26: =D21*Assumptions!$B$28 -> 0
A27: R&D / engineering | B27: =B21*Assumptions!$B$29 -> 0 | C27: =C21*Assumptions!$B$29 -> 0 | D27: =D21*Assumptions!$B$29 -> 0
A28: General & administrative | B28: =Assumptions!$B$30 -> 0 | C28: =Assumptions!$B$30 -> 0 | D28: =Assumptions!$B$30 -> 0
A30: Operating Income (Loss) | B30: =B24-SUM(B26:B28) -> 260367.2 | C30: =C24-SUM(C26:C28) -> 1813270.4 | D30: =D24-SUM(D26:D28) -> 16641111

Sheet Notes
A1: How to use this model
A2: 1. Go to the Assumptions tab. Every yellow cell is an input. Pricing rows (Core ACV midpoints, Campus per-student rate) are pre-filled with real figures from the internal pricing schedule — leave these unless your actual pricing has changed.
A3: 2. Fill in customer growth assumptions: how many new customers per segment you expect to add in Year 1, Year 2, and Year 3, plus an annual churn % for each segment. These default to 0, which will make the Projection tab show $0 until you enter real numbers — that is intentional, not an error.
A4: 3. Fill in cost assumptions (COGS %, S&M %, R&D %, G&A $/year). These also default to 0.
A5: 4. The '3-Year Projection' tab is 100% formulas — nothing is hardcoded. Change any assumption and the whole model recalculates.
A7: What's real vs. what needs your input
A8: Real, sourced figures: Core plan pricing ranges and the $1.40/student Campus rate, both from the internal pricing schedule referenced elsewhere in this project.
A9: Needs your input, currently 0 / placeholder: every customer-count and churn assumption, every cost assumption, and the Venue blended ACV (no specific per-tier dollar figure was found in any document reviewed — only that Venue pricing is tiered by capacity).
A11: Model simplifications, stated plainly
A12: Revenue for each year is computed off that year's ending customer count × ACV (a run-rate approximation), not a month-by-month ramp. This is a reasonable simplification for an early 3-year model but will overstate Year 1 revenue somewhat for any customer who doesn't sign on day one of the year — worth refining later with actual contract start dates.
A13: Churn is applied to the prior year's ending base before adding that year's new customers.
A14: Enterprise/Statewide pricing has an extremely wide range ($720K–$10M+) — the model uses the simple average as a placeholder midpoint, which is unlikely to be representative for this tier specifically. If you expect any Enterprise/Statewide deals, override that ACV manually with a realistic deal-size assumption rather than relying on the averaged midpoint.
... A17: This is not a substitute for an actual financial plan built with your management team's real pipeline, hiring plan, and cost structure. It's a correctly-wired calculation engine waiting for your real numbers — treat the current file (all zeros) as a template, not a forecast.
